{"air_temp_max": {"1901": [{"min": 123.0, "max": 125.0, "mean": 123.9, "count": 10}], "1902": [{"min": 116.0, "max": 118.0, "mean": 117.4, "count": 10}], "1903": [{"min": 133.0, "max": 135.0, "mean": 133.8, "count": 10}], "1904": [{"min": 132.0, "max": 134.0, "mean": 133.2, "count": 10}], "1905": [{"min": 125.0, "max": 127.0, "mean": 125.8, "count": 10}], "1906": [{"min": 132.0, "max": 134.0, "mean": 133.2, "count": 10}], "1907": [{"min": 125.0, "max": 127.0, "mean": 126.5, "count": 10}], "1908": [{"min": 122.0, "max": 124.0, "mean": 123.4, "count": 10}], "1909": [{"min": 121.0, "max": 124.0, "mean": 122.6, "count": 10}], "1910": [{"min": 132.0, "max": 134.0, "mean": 133.5, "count": 10}], "1911": [{"min": 143.0, "max": 146.0, "mean": 144.6, "count": 10}], "1912": [{"min": 127.0, "max": 130.0, "mean": 128.6, "count": 10}], "1913": [{"min": 134.0, "max": 136.0, "mean": 134.8, "count": 10}], "1914": [{"min": 133.0, "max": 135.0, "mean": 134.1, "count": 10}], "1915": [{"min": 126.0, "max": 128.0, "mean": 126.8, "count": 10}], "1916": [{"min": 131.0, "max": 133.0, "mean": 132.1, "count": 10}], "1917": [{"min": 123.0, "max": 125.0, "mean": 124.1, "count": 10}], "1918": [{"min": 135.0, "max": 137.0, "mean": 136.1, "count": 10}], "1919": [{"min": 120.0, "max": 122.0, "mean": 121.3, "count": 10}], "1920": [{"min": 136.0, "max": 138.0, "mean": 137.4, "count": 10}], "1921": [{"min": 143.0, "max": 145.0, "mean": 144.5, "count": 10}], "1922": [{"min": 116.0, "max": 118.0, "mean": 117.5, "count": 10}], "1923": [{"min": 125.0, "max": 127.0, "mean": 126.2, "count": 10}], "1924": [{"min": 123.0, "max": 125.0, "mean": 123.8, "count": 10}], "1925": [{"min": 130.0, "max": 132.0, "mean": 131.4, "count": 10}], "1926": [{"min": 132.0, "max": 134.0, "mean": 133.4, "count": 10}], "1927": [{"min": 125.0, "max": 127.0, "mean": 126.1, "count": 10}], "1928": [{"min": 131.0, "max": 133.0, "mean": 132.5, "count": 10}], "1929": [{"min": 124.0, "max": 126.0, "mean": 125.2, "count": 10}], "1930": [{"min": 134.0, "max": 136.0, "mean": 135.2, "count": 10}], "1931": [{"min": 123.0, "max": 125.0, "mean": 124.0, "count": 10}], "1932": [{"min": 130.0, "max": 133.0, "mean": 131.7, "count": 10}], "1933": [{"min": 124.0, "max": 126.0, "mean": 125.6, "count": 10}], "1934": [{"min": 147.0, "max": 149.0, "mean": 148.2, "count": 10}], "1935": [{"min": 132.0, "max": 135.0, "mean": 133.7, "count": 10}], "1936": [{"min": 131.0, "max": 133.0, "mean": 132.0, "count": 10}], "1937": [{"min": 133.0, "max": 135.0, "mean": 134.0, "count": 10}], "1938": [{"min": 134.0, "max": 137.0, "mean": 135.8, "count": 10}], "1939": [{"min": 128.0, "max": 130.0, "mean": 129.2, "count": 10}], "1940": [{"min": 112.0, "max": 114.0, "mean": 113.2, "count": 10}], "1941": [{"min": 116.0, "max": 118.0, "mean": 117.3, "count": 10}], "1942": [{"min": 121.0, "max": 123.0, "mean": 122.3, "count": 10}], "1943": [{"min": 141.0, "max": 143.0, "mean": 142.6, "count": 10}], "1944": [{"min": 129.0, "max": 131.0, "mean": 129.9, "count": 10}], "1945": [{"min": 138.0, "max": 140.0, "mean": 139.1, "count": 10}], "1946": [{"min": 135.0, "max": 137.0, "mean": 136.2, "count": 10}], "1947": [{"min": 136.0, "max": 138.0, "mean": 137.1, "count": 10}], "1948": [{"min": 142.0, "max": 145.0, "mean": 143.5, "count": 10}], "1949": [{"min": 144.0, "max": 146.0, "mean": 145.5, "count": 10}], "1950": [{"min": 134.0, "max": 136.0, "mean": 135.1, "count": 10}], "1951": [{"min": 137.0, "max": 139.0, "mean": 138.0, "count": 10}], "1952": [{"min": 124.0, "max": 126.0, "mean": 125.4, "count": 10}], "1953": [{"min": 143.0, "max": 145.0, "mean": 144.1, "count": 10}], "1954": [{"min": 124.0, "max": 126.0, "mean": 125.3, "count": 10}], "1955": [{"min": 121.0, "max": 123.0, "mean": 122.2, "count": 10}], "1956": [{"min": 113.0, "max": 115.0, "mean": 114.4, "count": 10}], "1957": [{"min": 134.0, "max": 136.0, "mean": 135.1, "count": 10}], "1958": [{"min": 128.0, "max": 130.0, "mean": 129.2, "count": 10}], "1959": [{"min": 145.0, "max": 147.0, "mean": 146.2, "count": 10}], "1960": [{"min": 129.0, "max": 131.0, "mean": 130.6, "count": 10}], "1961": [{"min": 139.0, "max": 141.0, "mean": 140.5, "count": 10}], "1962": [{"min": 119.0, "max": 122.0, "mean": 120.7, "count": 10}], "1963": [{"min": 121.0, "max": 123.0, "mean": 122.5, "count": 10}], "1964": [{"min": 131.0, "max": 133.0, "mean": 132.1, "count": 10}], "1965": [{"min": 122.0, "max": 124.0, "mean": 123.1, "count": 10}], "1966": [{"min": 131.0, "max": 134.0, "mean": 132.5, "count": 10}], "1967": [{"min": 136.0, "max": 138.0, "mean": 137.5, "count": 10}], "1968": [{"min": 126.0, "max": 128.0, "mean": 127.1, "count": 10}], "1969": [{"min": 122.0, "max": 124.0, "mean": 123.3, "count": 10}], "1970": [{"min": 120.0, "max": 122.0, "mean": 121.1, "count": 10}], "1971": [{"min": 133.0, "max": 135.0, "mean": 134.4, "count": 10}], "1972": [{"min": 124.0, "max": 126.0, "mean": 125.0, "count": 10}], "1973": [{"min": 129.0, "max": 131.0, "mean": 130.1, "count": 10}], "1974": [{"min": 132.0, "max": 134.0, "mean": 133.2, "count": 10}], "1975": [{"min": 136.0, "max": 138.0, "mean": 137.2, "count": 10}], "1976": [{"min": 134.0, "max": 136.0, "mean": 134.8, "count": 10}], "1977": [{"min": 131.0, "max": 133.0, "mean": 132.4, "count": 10}], "1978": [{"min": 122.0, "max": 124.0, "mean": 123.1, "count": 10}], "1979": [{"min": 123.0, "max": 125.0, "mean": 123.8, "count": 10}], "1980": [{"min": 120.0, "max": 122.0, "mean": 121.1, "count": 10}], "1981": [{"min": 124.0, "max": 126.0, "mean": 125.5, "count": 10}], "1982": [{"min": 140.0, "max": 142.0, "mean": 140.9, "count": 10}], "1983": [{"min": 137.0, "max": 139.0, "mean": 138.2, "count": 10}], "1984": [{"min": 121.0, "max": 123.0, "mean": 122.1, "count": 10}], "1985": [{"min": 120.0, "max": 122.0, "mean": 121.0, "count": 10}], "1986": [{"min": 124.0, "max": 126.0, "mean": 125.2, "count": 10}], "1987": [{"min": 115.0, "max": 117.0, "mean": 116.3, "count": 10}], "1988": [{"min": 135.0, "max": 137.0, "mean": 136.1, "count": 10}], "1989": [{"min": 146.0, "max": 148.0, "mean": 147.0, "count": 10}], "1990": [{"min": 143.0, "max": 145.0, "mean": 144.3, "count": 10}], "1991": [{"min": 134.0, "max": 137.0, "mean": 135.8, "count": 10}], "1992": [{"min": 142.0, "max": 144.0, "mean": 142.9, "count": 10}], "1993": [{"min": 130.0, "max": 132.0, "mean": 131.5, "count": 10}], "1994": [{"min": 144.0, "max": 146.0, "mean": 145.6, "count": 10}], "1995": [{"min": 136.0, "max": 138.0, "mean": 137.0, "count": 10}], "1996": [{"min": 113.0, "max": 115.0, "mean": 114.1, "count": 10}], "1997": [{"min": 137.0, "max": 139.0, "mean": 138.0, "count": 10}], "1998": [{"min": 137.0, "max": 140.0, "mean": 138.6, "count": 10}], "1999": [{"min": 143.0, "max": 145.0, "mean": 144.0, "count": 10}], "2000": [{"min": 148.0, "max": 150.0, "mean": 149.3, "count": 10}], "2001": [{"min": 137.0, "max": 139.0, "mean": 138.1, "count": 10}], "2002": [{"min": 139.0, "max": 141.0, "mean": 140.2, "count": 10}], "2003": [{"min": 145.0, "max": 147.0, "mean": 146.5, "count": 10}], "2004": [{"min": 136.0, "max": 138.0, "mean": 137.4, "count": 10}], "2005": [{"min": 140.0, "max": 142.0, "mean": 141.1, "count": 10}], "2006": [{"min": 144.0, "max": 146.0, "mean": 145.1, "count": 10}], "2007": [{"min": 147.0, "max": 150.0, "mean": 148.6, "count": 10}], "2008": [{"min": 143.0, "max": 145.0, "mean": 144.1, "count": 10}], "2009": [{"min": 140.0, "max": 141.0, "mean": 140.5, "count": 10}], "2010": [{"min": 124.0, "max": 126.0, "mean": 125.1, "count": 10}], "2011": [{"min": 151.0, "max": 153.0, "mean": 152.1, "count": 10}], "2012": [{"min": 142.0, "max": 144.0, "mean": 143.1, "count": 10}], "2013": [{"min": 130.0, "max": 133.0, "mean": 131.8, "count": 10}], "2014": [{"min": 153.0, "max": 155.0, "mean": 154.4, "count": 10}], "2015": [{"min": 151.0, "max": 153.0, "mean": 152.2, "count": 10}], "2016": [{"min": 145.0, "max": 147.0, "mean": 146.2, "count": 10}], "2017": [{"min": 145.0, "max": 147.0, "mean": 146.5, "count": 10}], "2018": [{"min": 160.0, "max": 162.0, "mean": 160.9, "count": 10}], "2019": [{"min": 158.0, "max": 160.0, "mean": 159.1, "count": 10}], "2020": [{"min": 158.0, "max": 160.0, "mean": 159.1, "count": 10}], "2021": [{"min": 139.0, "max": 141.0, "mean": 140.4, "count": 10}], "2022": [{"min": 161.0, "max": 163.0, "mean": 162.1, "count": 10}], "2023": [{"min": 158.0, "max": 160.0, "mean": 159.0, "count": 10}], "2024": [{"min": 162.0, "max": 164.0, "mean": 163.1, "count": 10}], "2025": [{"min": 154.0, "max": 155.0, "mean": 154.5, "count": 10}]}, "air_temp_mean": {"1881": [{"min": 75.0, "max": 77.0, "mean": 75.7, "count": 10}], "1882": [{"min": 87.0, "max": 88.0, "mean": 87.5, "count": 10}], "1883": [{"min": 82.0, "max": 84.0, "mean": 82.8, "count": 10}], "1884": [{"min": 88.0, "max": 89.0, "mean": 88.5, "count": 10}], "1885": [{"min": 80.0, "max": 82.0, "mean": 81.4, "count": 10}], "1886": [{"min": 83.0, "max": 84.0, "mean": 83.5, "count": 10}], "1887": [{"min": 71.0, "max": 73.0, "mean": 71.8, "count": 10}], "1888": [{"min": 72.0, "max": 73.0, "mean": 72.5, "count": 10}], "1889": [{"min": 76.0, "max": 78.0, "mean": 77.2, "count": 10}], "1890": [{"min": 75.0, "max": 77.0, "mean": 76.1, "count": 10}], "1891": [{"min": 75.0, "max": 77.0, "mean": 76.0, "count": 10}], "1892": [{"min": 76.0, "max": 77.0, "mean": 76.6, "count": 10}], "1893": [{"min": 79.0, "max": 81.0, "mean": 80.1, "count": 10}], "1894": [{"min": 81.0, "max": 83.0, "mean": 82.3, "count": 10}], "1895": [{"min": 73.0, "max": 75.0, "mean": 74.1, "count": 10}], "1896": [{"min": 76.0, "max": 77.0, "mean": 76.6, "count": 10}], "1897": [{"min": 80.0, "max": 82.0, "mean": 80.9, "count": 10}], "1898": [{"min": 86.0, "max": 88.0, "mean": 86.7, "count": 10}], "1899": [{"min": 81.0, "max": 83.0, "mean": 81.7, "count": 10}], "1900": [{"min": 85.0, "max": 86.0, "mean": 85.6, "count": 10}], "1901": [{"min": 75.0, "max": 77.0, "mean": 76.4, "count": 10}], "1902": [{"min": 71.0, "max": 73.0, "mean": 72.4, "count": 10}], "1903": [{"min": 88.0, "max": 90.0, "mean": 88.8, "count": 10}], "1904": [{"min": 87.0, "max": 89.0, "mean": 88.3, "count": 10}], "1905": [{"min": 82.0, "max": 84.0, "mean": 83.3, "count": 10}], "1906": [{"min": 86.0, "max": 88.0, "mean": 87.1, "count": 10}], "1907": [{"min": 80.0, "max": 82.0, "mean": 81.4, "count": 10}], "1908": [{"min": 76.0, "max": 78.0, "mean": 77.2, "count": 10}], "1909": [{"min": 76.0, "max": 78.0, "mean": 77.0, "count": 10}], "1910": [{"min": 86.0, "max": 88.0, "mean": 87.2, "count": 10}], "1911": [{"min": 94.0, "max": 95.0, "mean": 94.8, "count": 10}], "1912": [{"min": 82.0, "max": 83.0, "mean": 82.6, "count": 10}], "1913": [{"min": 88.0, "max": 89.0, "mean": 88.6, "count": 10}], "1914": [{"min": 87.0, "max": 89.0, "mean": 87.8, "count": 10}], "1915": [{"min": 81.0, "max": 83.0, "mean": 82.1, "count": 10}], "1916": [{"min": 87.0, "max": 88.0, "mean": 87.7, "count": 10}], "1917": [{"min": 77.0, "max": 78.0, "mean": 77.5, "count": 10}], "1918": [{"min": 89.0, "max": 90.0, "mean": 89.6, "count": 10}], "1919": [{"min": 75.0, "max": 76.0, "mean": 75.6, "count": 10}], "1920": [{"min": 88.0, "max": 90.0, "mean": 89.2, "count": 10}], "1921": [{"min": 91.0, "max": 92.0, "mean": 91.7, "count": 10}], "1922": [{"min": 72.0, "max": 74.0, "mean": 73.3, "count": 10}], "1923": [{"min": 82.0, "max": 84.0, "mean": 83.0, "count": 10}], "1924": [{"min": 79.0, "max": 80.0, "mean": 79.7, "count": 10}], "1925": [{"min": 87.0, "max": 89.0, "mean": 88.2, "count": 10}], "1926": [{"min": 90.0, "max": 92.0, "mean": 90.9, "count": 10}], "1927": [{"min": 82.0, "max": 84.0, "mean": 83.2, "count": 10}], "1928": [{"min": 85.0, "max": 86.0, "mean": 85.6, "count": 10}], "1929": [{"min": 76.0, "max": 77.0, "mean": 76.7, "count": 10}], "1930": [{"min": 91.0, "max": 92.0, "mean": 91.6, "count": 10}], "1931": [{"min": 80.0, "max": 81.0, "mean": 80.7, "count": 10}], "1932": [{"min": 86.0, "max": 88.0, "mean": 87.0, "count": 10}], "1933": [{"min": 77.0, "max": 79.0, "mean": 77.8, "count": 10}], "1934": [{"min": 100.0, "max": 102.0, "mean": 100.8, "count": 10}], "1935": [{"min": 87.0, "max": 89.0, "mean": 88.4, "count": 10}], "1936": [{"min": 87.0, "max": 89.0, "mean": 88.1, "count": 10}], "1937": [{"min": 89.0, "max": 90.0, "mean": 89.7, "count": 10}], "1938": [{"min": 88.0, "max": 89.0, "mean": 88.7, "count": 10}], "1939": [{"min": 85.0, "max": 87.0, "mean": 86.3, "count": 10}], "1940": [{"min": 66.0, "max": 68.0, "mean": 67.0, "count": 10}], "1941": [{"min": 74.0, "max": 76.0, "mean": 74.8, "count": 10}], "1942": [{"min": 75.0, "max": 77.0, "mean": 76.0, "count": 10}], "1943": [{"min": 94.0, "max": 95.0, "mean": 94.6, "count": 10}], "1944": [{"min": 87.0, "max": 89.0, "mean": 88.3, "count": 10}], "1945": [{"min": 94.0, "max": 96.0, "mean": 95.1, "count": 10}], "1946": [{"min": 87.0, "max": 88.0, "mean": 87.6, "count": 10}], "1947": [{"min": 86.0, "max": 88.0, "mean": 87.2, "count": 10}], "1948": [{"min": 96.0, "max": 97.0, "mean": 96.6, "count": 10}], "1949": [{"min": 96.0, "max": 97.0, "mean": 96.6, "count": 10}], "1950": [{"min": 89.0, "max": 91.0, "mean": 89.9, "count": 10}], "1951": [{"min": 92.0, "max": 93.0, "mean": 92.7, "count": 10}], "1952": [{"min": 83.0, "max": 85.0, "mean": 83.9, "count": 10}], "1953": [{"min": 96.0, "max": 97.0, "mean": 96.5, "count": 10}], "1954": [{"min": 81.0, "max": 83.0, "mean": 82.2, "count": 10}], "1955": [{"min": 78.0, "max": 79.0, "mean": 78.5, "count": 10}], "1956": [{"min": 71.0, "max": 72.0, "mean": 71.5, "count": 10}], "1957": [{"min": 90.0, "max": 92.0, "mean": 91.2, "count": 10}], "1958": [{"min": 86.0, "max": 88.0, "mean": 87.4, "count": 10}], "1959": [{"min": 94.0, "max": 95.0, "mean": 94.7, "count": 10}], "1960": [{"min": 87.0, "max": 88.0, "mean": 87.7, "count": 10}], "1961": [{"min": 93.0, "max": 94.0, "mean": 93.7, "count": 10}], "1962": [{"min": 74.0, "max": 76.0, "mean": 74.8, "count": 10}], "1963": [{"min": 74.0, "max": 75.0, "mean": 74.7, "count": 10}], "1964": [{"min": 84.0, "max": 86.0, "mean": 85.1, "count": 10}], "1965": [{"min": 78.0, "max": 80.0, "mean": 78.9, "count": 10}], "1966": [{"min": 89.0, "max": 90.0, "mean": 89.6, "count": 10}], "1967": [{"min": 94.0, "max": 96.0, "mean": 94.9, "count": 10}], "1968": [{"min": 84.0, "max": 86.0, "mean": 84.9, "count": 10}], "1969": [{"min": 79.0, "max": 81.0, "mean": 80.2, "count": 10}], "1970": [{"min": 80.0, "max": 82.0, "mean": 81.1, "count": 10}], "1971": [{"min": 87.0, "max": 89.0, "mean": 88.3, "count": 10}], "1972": [{"min": 80.0, "max": 82.0, "mean": 81.1, "count": 10}], "1973": [{"min": 85.0, "max": 86.0, "mean": 85.7, "count": 10}], "1974": [{"min": 91.0, "max": 93.0, "mean": 92.1, "count": 10}], "1975": [{"min": 93.0, "max": 94.0, "mean": 93.6, "count": 10}], "1976": [{"min": 87.0, "max": 89.0, "mean": 88.1, "count": 10}], "1977": [{"min": 89.0, "max": 91.0, "mean": 90.5, "count": 10}], "1978": [{"min": 81.0, "max": 82.0, "mean": 81.7, "count": 10}], "1979": [{"min": 79.0, "max": 81.0, "mean": 80.3, "count": 10}], "1980": [{"min": 79.0, "max": 80.0, "mean": 79.7, "count": 10}], "1981": [{"min": 85.0, "max": 86.0, "mean": 85.7, "count": 10}], "1982": [{"min": 95.0, "max": 96.0, "mean": 95.6, "count": 10}], "1983": [{"min": 94.0, "max": 95.0, "mean": 94.7, "count": 10}], "1984": [{"min": 82.0, "max": 84.0, "mean": 82.9, "count": 10}], "1985": [{"min": 77.0, "max": 79.0, "mean": 78.3, "count": 10}], "1986": [{"min": 82.0, "max": 84.0, "mean": 82.8, "count": 10}], "1987": [{"min": 75.0, "max": 77.0, "mean": 75.9, "count": 10}], "1988": [{"min": 95.0, "max": 96.0, "mean": 95.7, "count": 10}], "1989": [{"min": 99.0, "max": 101.0, "mean": 100.3, "count": 10}], "1990": [{"min": 99.0, "max": 101.0, "mean": 99.8, "count": 10}], "1991": [{"min": 86.0, "max": 87.0, "mean": 86.7, "count": 10}], "1992": [{"min": 96.0, "max": 98.0, "mean": 96.9, "count": 10}], "1993": [{"min": 86.0, "max": 87.0, "mean": 86.6, "count": 10}], "1994": [{"min": 100.0, "max": 101.0, "mean": 100.6, "count": 10}], "1995": [{"min": 92.0, "max": 93.0, "mean": 92.4, "count": 10}], "1996": [{"min": 71.0, "max": 73.0, "mean": 71.8, "count": 10}], "1997": [{"min": 90.0, "max": 91.0, "mean": 90.6, "count": 10}], "1998": [{"min": 94.0, "max": 96.0, "mean": 94.7, "count": 10}], "1999": [{"min": 97.0, "max": 99.0, "mean": 98.3, "count": 10}], "2000": [{"min": 103.0, "max": 104.0, "mean": 103.7, "count": 10}], "2001": [{"min": 93.0, "max": 95.0, "mean": 94.1, "count": 10}], "2002": [{"min": 96.0, "max": 98.0, "mean": 96.9, "count": 10}], "2003": [{"min": 95.0, "max": 97.0, "mean": 96.3, "count": 10}], "2004": [{"min": 93.0, "max": 94.0, "mean": 93.6, "count": 10}], "2005": [{"min": 93.0, "max": 94.0, "mean": 93.5, "count": 10}], "2006": [{"min": 95.0, "max": 97.0, "mean": 96.4, "count": 10}], "2007": [{"min": 100.0, "max": 102.0, "mean": 101.4, "count": 10}], "2008": [{"min": 96.0, "max": 99.0, "mean": 97.5, "count": 10}], "2009": [{"min": 93.0, "max": 95.0, "mean": 93.8, "count": 10}], "2010": [{"min": 79.0, "max": 81.0, "mean": 79.9, "count": 10}], "2011": [{"min": 98.0, "max": 100.0, "mean": 98.9, "count": 10}], "2012": [{"min": 93.0, "max": 96.0, "mean": 94.3, "count": 10}], "2013": [{"min": 89.0, "max": 90.0, "mean": 89.6, "count": 10}], "2014": [{"min": 105.0, "max": 107.0, "mean": 105.8, "count": 10}], "2015": [{"min": 102.0, "max": 104.0, "mean": 102.8, "count": 10}], "2016": [{"min": 98.0, "max": 100.0, "mean": 99.2, "count": 10}], "2017": [{"min": 99.0, "max": 101.0, "mean": 100.0, "count": 10}], "2018": [{"min": 107.0, "max": 109.0, "mean": 108.2, "count": 10}], "2019": [{"min": 106.0, "max": 108.0, "mean": 106.8, "count": 10}], "2020": [{"min": 107.0, "max": 109.0, "mean": 107.8, "count": 10}], "2021": [{"min": 92.0, "max": 94.0, "mean": 93.2, "count": 10}], "2022": [{"min": 107.0, "max": 109.0, "mean": 108.0, "count": 10}], "2023": [{"min": 110.0, "max": 112.0, "mean": 110.8, "count": 10}], "2024": [{"min": 113.0, "max": 115.0, "mean": 114.0, "count": 10}], "2025": [{"min": 101.0, "max": 103.0, "mean": 102.0, "count": 10}]}, "air_temp_min": {"1901": [{"min": 31.0, "max": 33.0, "mean": 32.2, "count": 10}], "1902": [{"min": 31.0, "max": 33.0, "mean": 31.8, "count": 10}], "1903": [{"min": 46.0, "max": 47.0, "mean": 46.5, "count": 10}], "1904": [{"min": 44.0, "max": 46.0, "mean": 45.3, "count": 10}], "1905": [{"min": 44.0, "max": 45.0, "mean": 44.4, "count": 10}], "1906": [{"min": 44.0, "max": 46.0, "mean": 45.3, "count": 10}], "1907": [{"min": 39.0, "max": 40.0, "mean": 39.6, "count": 10}], "1908": [{"min": 35.0, "max": 36.0, "mean": 35.6, "count": 10}], "1909": [{"min": 33.0, "max": 34.0, "mean": 33.6, "count": 10}], "1910": [{"min": 45.0, "max": 46.0, "mean": 45.5, "count": 10}], "1911": [{"min": 46.0, "max": 48.0, "mean": 46.8, "count": 10}], "1912": [{"min": 39.0, "max": 41.0, "mean": 39.8, "count": 10}], "1913": [{"min": 44.0, "max": 46.0, "mean": 45.1, "count": 10}], "1914": [{"min": 46.0, "max": 47.0, "mean": 46.7, "count": 10}], "1915": [{"min": 37.0, "max": 38.0, "mean": 37.7, "count": 10}], "1916": [{"min": 46.0, "max": 47.0, "mean": 46.6, "count": 10}], "1917": [{"min": 31.0, "max": 32.0, "mean": 31.6, "count": 10}], "1918": [{"min": 45.0, "max": 46.0, "mean": 45.6, "count": 10}], "1919": [{"min": 31.0, "max": 33.0, "mean": 31.8, "count": 10}], "1920": [{"min": 43.0, "max": 44.0, "mean": 43.6, "count": 10}], "1921": [{"min": 40.0, "max": 42.0, "mean": 41.4, "count": 10}], "1922": [{"min": 30.0, "max": 31.0, "mean": 30.4, "count": 10}], "1923": [{"min": 40.0, "max": 41.0, "mean": 40.5, "count": 10}], "1924": [{"min": 35.0, "max": 36.0, "mean": 35.7, "count": 10}], "1925": [{"min": 46.0, "max": 47.0, "mean": 46.4, "count": 10}], "1926": [{"min": 51.0, "max": 52.0, "mean": 51.6, "count": 10}], "1927": [{"min": 42.0, "max": 43.0, "mean": 42.7, "count": 10}], "1928": [{"min": 39.0, "max": 41.0, "mean": 39.8, "count": 10}], "1929": [{"min": 27.0, "max": 28.0, "mean": 27.6, "count": 10}], "1930": [{"min": 47.0, "max": 49.0, "mean": 48.1, "count": 10}], "1931": [{"min": 36.0, "max": 38.0, "mean": 36.9, "count": 10}], "1932": [{"min": 43.0, "max": 44.0, "mean": 43.4, "count": 10}], "1933": [{"min": 33.0, "max": 34.0, "mean": 33.5, "count": 10}], "1934": [{"min": 55.0, "max": 56.0, "mean": 55.4, "count": 10}], "1935": [{"min": 43.0, "max": 44.0, "mean": 43.7, "count": 10}], "1936": [{"min": 48.0, "max": 49.0, "mean": 48.3, "count": 10}], "1937": [{"min": 49.0, "max": 50.0, "mean": 49.7, "count": 10}], "1938": [{"min": 47.0, "max": 48.0, "mean": 47.5, "count": 10}], "1939": [{"min": 47.0, "max": 48.0, "mean": 47.5, "count": 10}], "1940": [{"min": 25.0, "max": 26.0, "mean": 25.5, "count": 10}], "1941": [{"min": 34.0, "max": 35.0, "mean": 34.5, "count": 10}], "1942": [{"min": 32.0, "max": 33.0, "mean": 32.5, "count": 10}], "1943": [{"min": 48.0, "max": 49.0, "mean": 48.5, "count": 10}], "1944": [{"min": 46.0, "max": 47.0, "mean": 46.5, "count": 10}], "1945": [{"min": 51.0, "max": 53.0, "mean": 51.9, "count": 10}], "1946": [{"min": 44.0, "max": 46.0, "mean": 45.1, "count": 10}], "1947": [{"min": 34.0, "max": 36.0, "mean": 34.8, "count": 10}], "1948": [{"min": 49.0, "max": 51.0, "mean": 50.0, "count": 10}], "1949": [{"min": 48.0, "max": 49.0, "mean": 48.7, "count": 10}], "1950": [{"min": 45.0, "max": 46.0, "mean": 45.7, "count": 10}], "1951": [{"min": 49.0, "max": 50.0, "mean": 49.6, "count": 10}], "1952": [{"min": 42.0, "max": 43.0, "mean": 42.5, "count": 10}], "1953": [{"min": 50.0, "max": 51.0, "mean": 50.3, "count": 10}], "1954": [{"min": 40.0, "max": 41.0, "mean": 40.5, "count": 10}], "1955": [{"min": 35.0, "max": 36.0, "mean": 35.6, "count": 10}], "1956": [{"min": 30.0, "max": 31.0, "mean": 30.6, "count": 10}], "1957": [{"min": 48.0, "max": 49.0, "mean": 48.5, "count": 10}], "1958": [{"min": 48.0, "max": 49.0, "mean": 48.3, "count": 10}], "1959": [{"min": 45.0, "max": 46.0, "mean": 45.5, "count": 10}], "1960": [{"min": 48.0, "max": 49.0, "mean": 48.5, "count": 10}], "1961": [{"min": 52.0, "max": 53.0, "mean": 52.6, "count": 10}], "1962": [{"min": 33.0, "max": 34.0, "mean": 33.6, "count": 10}], "1963": [{"min": 30.0, "max": 31.0, "mean": 30.5, "count": 10}], "1964": [{"min": 41.0, "max": 42.0, "mean": 41.5, "count": 10}], "1965": [{"min": 36.0, "max": 38.0, "mean": 36.7, "count": 10}], "1966": [{"min": 49.0, "max": 50.0, "mean": 49.3, "count": 10}], "1967": [{"min": 52.0, "max": 53.0, "mean": 52.6, "count": 10}], "1968": [{"min": 45.0, "max": 46.0, "mean": 45.2, "count": 10}], "1969": [{"min": 39.0, "max": 40.0, "mean": 39.6, "count": 10}], "1970": [{"min": 42.0, "max": 43.0, "mean": 42.6, "count": 10}], "1971": [{"min": 44.0, "max": 46.0, "mean": 44.7, "count": 10}], "1972": [{"min": 40.0, "max": 42.0, "mean": 40.9, "count": 10}], "1973": [{"min": 44.0, "max": 45.0, "mean": 44.6, "count": 10}], "1974": [{"min": 53.0, "max": 54.0, "mean": 53.7, "count": 10}], "1975": [{"min": 53.0, "max": 54.0, "mean": 53.6, "count": 10}], "1976": [{"min": 43.0, "max": 44.0, "mean": 43.5, "count": 10}], "1977": [{"min": 52.0, "max": 53.0, "mean": 52.8, "count": 10}], "1978": [{"min": 43.0, "max": 45.0, "mean": 44.3, "count": 10}], "1979": [{"min": 40.0, "max": 42.0, "mean": 40.9, "count": 10}], "1980": [{"min": 40.0, "max": 42.0, "mean": 40.8, "count": 10}], "1981": [{"min": 46.0, "max": 47.0, "mean": 46.5, "count": 10}], "1982": [{"min": 51.0, "max": 53.0, "mean": 52.2, "count": 10}], "1983": [{"min": 51.0, "max": 53.0, "mean": 52.2, "count": 10}], "1984": [{"min": 46.0, "max": 47.0, "mean": 46.6, "count": 10}], "1985": [{"min": 37.0, "max": 38.0, "mean": 37.5, "count": 10}], "1986": [{"min": 40.0, "max": 42.0, "mean": 41.0, "count": 10}], "1987": [{"min": 36.0, "max": 37.0, "mean": 36.6, "count": 10}], "1988": [{"min": 55.0, "max": 56.0, "mean": 55.6, "count": 10}], "1989": [{"min": 56.0, "max": 58.0, "mean": 56.9, "count": 10}], "1990": [{"min": 55.0, "max": 57.0, "mean": 56.0, "count": 10}], "1991": [{"min": 40.0, "max": 41.0, "mean": 40.6, "count": 10}], "1992": [{"min": 52.0, "max": 53.0, "mean": 52.6, "count": 10}], "1993": [{"min": 43.0, "max": 44.0, "mean": 43.6, "count": 10}], "1994": [{"min": 56.0, "max": 58.0, "mean": 57.3, "count": 10}], "1995": [{"min": 49.0, "max": 50.0, "mean": 49.6, "count": 10}], "1996": [{"min": 33.0, "max": 34.0, "mean": 33.4, "count": 10}], "1997": [{"min": 47.0, "max": 49.0, "mean": 47.8, "count": 10}], "1998": [{"min": 54.0, "max": 56.0, "mean": 55.1, "count": 10}], "1999": [{"min": 56.0, "max": 57.0, "mean": 56.7, "count": 10}], "2000": [{"min": 60.0, "max": 61.0, "mean": 60.5, "count": 10}], "2001": [{"min": 52.0, "max": 54.0, "mean": 52.9, "count": 10}], "2002": [{"min": 55.0, "max": 57.0, "mean": 56.3, "count": 10}], "2003": [{"min": 46.0, "max": 47.0, "mean": 46.6, "count": 10}], "2004": [{"min": 49.0, "max": 50.0, "mean": 49.8, "count": 10}], "2005": [{"min": 46.0, "max": 47.0, "mean": 46.7, "count": 10}], "2006": [{"min": 45.0, "max": 47.0, "mean": 46.1, "count": 10}], "2007": [{"min": 51.0, "max": 54.0, "mean": 52.1, "count": 10}], "2008": [{"min": 50.0, "max": 52.0, "mean": 50.5, "count": 10}], "2009": [{"min": 45.0, "max": 48.0, "mean": 45.7, "count": 10}], "2010": [{"min": 31.0, "max": 34.0, "mean": 31.8, "count": 10}], "2011": [{"min": 45.0, "max": 49.0, "mean": 46.4, "count": 10}], "2012": [{"min": 44.0, "max": 47.0, "mean": 44.6, "count": 10}], "2013": [{"min": 50.0, "max": 51.0, "mean": 50.6, "count": 10}], "2014": [{"min": 57.0, "max": 60.0, "mean": 58.0, "count": 10}], "2015": [{"min": 51.0, "max": 54.0, "mean": 51.7, "count": 10}], "2016": [{"min": 51.0, "max": 54.0, "mean": 51.8, "count": 10}], "2017": [{"min": 52.0, "max": 55.0, "mean": 53.0, "count": 10}], "2018": [{"min": 53.0, "max": 56.0, "mean": 53.9, "count": 10}], "2019": [{"min": 51.0, "max": 54.0, "mean": 52.0, "count": 10}], "2020": [{"min": 53.0, "max": 57.0, "mean": 54.4, "count": 10}], "2021": [{"min": 46.0, "max": 49.0, "mean": 46.8, "count": 10}], "2022": [{"min": 52.0, "max": 55.0, "mean": 52.8, "count": 10}], "2023": [{"min": 60.0, "max": 62.0, "mean": 60.6, "count": 10}], "2024": [{"min": 64.0, "max": 66.0, "mean": 64.5, "count": 10}], "2025": [{"min": 48.0, "max": 51.0, "mean": 49.0, "count": 10}]}, "drought_index": {"1995": [{"min": 31.0, "max": 32.0, "mean": 31.5, "count": 10}], "1996": [{"min": 31.0, "max": 33.0, "mean": 31.7, "count": 10}], "1997": [{"min": 27.0, "max": 29.0, "mean": 28.0, "count": 10}], "1998": [{"min": 28.0, "max": 29.0, "mean": 28.4, "count": 10}], "1999": [{"min": 26.0, "max": 27.0, "mean": 26.4, "count": 10}], "2000": [{"min": 28.0, "max": 30.0, "mean": 28.9, "count": 10}], "2001": [{"min": 29.0, "max": 31.0, "mean": 29.9, "count": 10}], "2002": [{"min": 35.0, "max": 37.0, "mean": 35.5, "count": 10}], "2003": [{"min": 20.0, "max": 22.0, "mean": 21.2, "count": 10}], "2004": [{"min": 28.0, "max": 29.0, "mean": 28.4, "count": 10}], "2005": [{"min": 26.0, "max": 28.0, "mean": 26.6, "count": 10}], "2006": [{"min": 23.0, "max": 24.0, "mean": 23.6, "count": 10}], "2007": [{"min": 36.0, "max": 37.0, "mean": 36.4, "count": 10}], "2008": [{"min": 25.0, "max": 26.0, "mean": 25.6, "count": 10}], "2009": [{"min": 31.0, "max": 33.0, "mean": 32.3, "count": 10}], "2010": [{"min": 35.0, "max": 37.0, "mean": 36.1, "count": 10}], "2011": [{"min": 22.0, "max": 23.0, "mean": 22.3, "count": 10}], "2012": [{"min": 25.0, "max": 26.0, "mean": 25.3, "count": 10}], "2013": [{"min": 29.0, "max": 30.0, "mean": 29.3, "count": 10}], "2014": [{"min": 23.0, "max": 24.0, "mean": 23.3, "count": 10}], "2015": [{"min": 22.0, "max": 23.0, "mean": 22.4, "count": 10}], "2016": [{"min": 21.0, "max": 23.0, "mean": 22.3, "count": 10}], "2017": [{"min": 28.0, "max": 30.0, "mean": 29.2, "count": 10}], "2018": [{"min": 15.0, "max": 16.0, "mean": 15.9, "count": 10}], "2019": [{"min": 20.0, "max": 21.0, "mean": 20.3, "count": 10}], "2020": [{"min": 23.0, "max": 24.0, "mean": 23.6, "count": 10}], "2021": [{"min": 32.0, "max": 33.0, "mean": 32.5, "count": 10}], "2022": [{"min": 20.0, "max": 21.0, "mean": 20.3, "count": 10}], "2023": [{"min": 28.0, "max": 30.0, "mean": 29.3, "count": 10}], "2024": [{"min": 26.0, "max": 27.0, "mean": 26.8, "count": 10}], "2025": [{"min": 21.0, "max": 22.0, "mean": 21.4, "count": 10}]}, "frost_days": {"1951": [{"min": 81.0, "max": 84.0, "mean": 82.4, "count": 10}], "1952": [{"min": 108.0, "max": 112.0, "mean": 109.9, "count": 10}], "1953": [{"min": 90.0, "max": 94.0, "mean": 92.0, "count": 10}], "1954": [{"min": 92.0, "max": 95.0, "mean": 93.4, "count": 10}], "1955": [{"min": 110.0, "max": 113.0, "mean": 111.3, "count": 10}], "1956": [{"min": 98.0, "max": 101.0, "mean": 99.7, "count": 10}], "1957": [{"min": 75.0, "max": 79.0, "mean": 76.9, "count": 10}], "1958": [{"min": 87.0, "max": 90.0, "mean": 88.5, "count": 10}], "1959": [{"min": 82.0, "max": 86.0, "mean": 84.0, "count": 10}], "1960": [{"min": 77.0, "max": 81.0, "mean": 79.4, "count": 10}], "1961": [{"min": 61.0, "max": 64.0, "mean": 62.7, "count": 10}], "1962": [{"min": 98.0, "max": 102.0, "mean": 100.0, "count": 10}], "1963": [{"min": 107.0, "max": 110.0, "mean": 108.7, "count": 10}], "1964": [{"min": 92.0, "max": 95.0, "mean": 93.7, "count": 10}], "1965": [{"min": 94.0, "max": 97.0, "mean": 95.3, "count": 10}], "1966": [{"min": 77.0, "max": 80.0, "mean": 78.9, "count": 10}], "1967": [{"min": 70.0, "max": 73.0, "mean": 71.6, "count": 10}], "1968": [{"min": 96.0, "max": 100.0, "mean": 98.1, "count": 10}], "1969": [{"min": 111.0, "max": 115.0, "mean": 113.4, "count": 10}], "1970": [{"min": 95.0, "max": 98.0, "mean": 96.7, "count": 10}], "1971": [{"min": 82.0, "max": 85.0, "mean": 83.7, "count": 10}], "1972": [{"min": 86.0, "max": 89.0, "mean": 87.8, "count": 10}], "1973": [{"min": 98.0, "max": 102.0, "mean": 100.0, "count": 10}], "1974": [{"min": 47.0, "max": 50.0, "mean": 48.8, "count": 10}], "1975": [{"min": 71.0, "max": 74.0, "mean": 72.8, "count": 10}], "1976": [{"min": 93.0, "max": 96.0, "mean": 94.7, "count": 10}], "1977": [{"min": 63.0, "max": 66.0, "mean": 64.7, "count": 10}], "1978": [{"min": 85.0, "max": 88.0, "mean": 86.7, "count": 10}], "1979": [{"min": 98.0, "max": 101.0, "mean": 99.7, "count": 10}], "1980": [{"min": 97.0, "max": 100.0, "mean": 98.7, "count": 10}], "1981": [{"min": 95.0, "max": 98.0, "mean": 96.9, "count": 10}], "1982": [{"min": 80.0, "max": 83.0, "mean": 81.7, "count": 10}], "1983": [{"min": 76.0, "max": 79.0, "mean": 77.7, "count": 10}], "1984": [{"min": 92.0, "max": 96.0, "mean": 94.0, "count": 10}], "1985": [{"min": 102.0, "max": 105.0, "mean": 103.7, "count": 10}], "1986": [{"min": 79.0, "max": 82.0, "mean": 80.7, "count": 10}], "1987": [{"min": 92.0, "max": 96.0, "mean": 94.2, "count": 10}], "1988": [{"min": 70.0, "max": 73.0, "mean": 71.8, "count": 10}], "1989": [{"min": 62.0, "max": 65.0, "mean": 63.7, "count": 10}], "1990": [{"min": 55.0, "max": 59.0, "mean": 57.0, "count": 10}], "1991": [{"min": 96.0, "max": 99.0, "mean": 97.8, "count": 10}], "1992": [{"min": 74.0, "max": 77.0, "mean": 75.4, "count": 10}], "1993": [{"min": 90.0, "max": 93.0, "mean": 91.4, "count": 10}], "1994": [{"min": 61.0, "max": 64.0, "mean": 62.3, "count": 10}], "1995": [{"min": 93.0, "max": 96.0, "mean": 94.3, "count": 10}], "1996": [{"min": 118.0, "max": 121.0, "mean": 119.8, "count": 10}], "1997": [{"min": 85.0, "max": 88.0, "mean": 86.4, "count": 10}], "1998": [{"min": 72.0, "max": 75.0, "mean": 73.5, "count": 10}], "1999": [{"min": 63.0, "max": 67.0, "mean": 65.0, "count": 10}], "2000": [{"min": 50.0, "max": 53.0, "mean": 51.8, "count": 10}], "2001": [{"min": 81.0, "max": 84.0, "mean": 82.7, "count": 10}], "2002": [{"min": 65.0, "max": 68.0, "mean": 66.4, "count": 10}], "2003": [{"min": 98.0, "max": 101.0, "mean": 99.7, "count": 10}], "2004": [{"min": 82.0, "max": 86.0, "mean": 84.0, "count": 10}], "2005": [{"min": 86.0, "max": 89.0, "mean": 87.7, "count": 10}], "2006": [{"min": 95.0, "max": 99.0, "mean": 97.6, "count": 10}], "2007": [{"min": 70.0, "max": 74.0, "mean": 72.6, "count": 10}], "2008": [{"min": 74.0, "max": 81.0, "mean": 79.1, "count": 10}], "2009": [{"min": 85.0, "max": 89.0, "mean": 87.4, "count": 10}], "2010": [{"min": 114.0, "max": 120.0, "mean": 117.9, "count": 10}], "2011": [{"min": 87.0, "max": 98.0, "mean": 94.3, "count": 10}], "2012": [{"min": 65.0, "max": 68.0, "mean": 66.3, "count": 10}], "2013": [{"min": 92.0, "max": 95.0, "mean": 93.7, "count": 10}], "2014": [{"min": 45.0, "max": 48.0, "mean": 46.0, "count": 10}], "2015": [{"min": 82.0, "max": 92.0, "mean": 88.7, "count": 10}], "2016": [{"min": 79.0, "max": 84.0, "mean": 82.3, "count": 10}], "2017": [{"min": 74.0, "max": 81.0, "mean": 78.5, "count": 10}], "2018": [{"min": 75.0, "max": 78.0, "mean": 76.5, "count": 10}], "2019": [{"min": 74.0, "max": 82.0, "mean": 79.2, "count": 10}], "2020": [{"min": 66.0, "max": 74.0, "mean": 71.6, "count": 10}], "2021": [{"min": 90.0, "max": 95.0, "mean": 93.2, "count": 10}], "2022": [{"min": 70.0, "max": 77.0, "mean": 74.5, "count": 10}], "2023": [{"min": 62.0, "max": 65.0, "mean": 63.5, "count": 10}], "2024": [{"min": 48.0, "max": 51.0, "mean": 49.7, "count": 10}], "2025": [{"min": 85.0, "max": 92.0, "mean": 89.4, "count": 10}]}, "hot_days": {"1951": [{"min": 5.0, "max": 6.0, "mean": 5.9, "count": 10}], "1952": [{"min": 9.0, "max": 10.0, "mean": 9.1, "count": 10}], "1953": [{"min": 6.0, "max": 6.0, "mean": 6.0, "count": 10}], "1954": [{"min": 5.0, "max": 6.0, "mean": 5.1, "count": 10}], "1955": [{"min": 2.0, "max": 2.0, "mean": 2.0, "count": 10}], "1956": [{"min": 1.0, "max": 1.0, "mean": 1.0, "count": 10}], "1957": [{"min": 9.0, "max": 9.0, "mean": 9.0, "count": 10}], "1958": [{"min": 3.0, "max": 3.0, "mean": 3.0, "count": 10}], "1959": [{"min": 6.0, "max": 6.0, "mean": 6.0, "count": 10}], "1960": [{"min": 2.0, "max": 2.0, "mean": 2.0, "count": 10}], "1961": [{"min": 8.0, "max": 9.0, "mean": 8.6, "count": 10}], "1962": [{"min": 3.0, "max": 3.0, "mean": 3.0, "count": 10}], "1963": [{"min": 6.0, "max": 6.0, "mean": 6.0, "count": 10}], "1964": [{"min": 14.0, "max": 14.0, "mean": 14.0, "count": 10}], "1965": [{"min": 2.0, "max": 2.0, "mean": 2.0, "count": 10}], "1966": [{"min": 5.0, "max": 5.0, "mean": 5.0, "count": 10}], "1967": [{"min": 6.0, "max": 6.0, "mean": 6.0, "count": 10}], "1968": [{"min": 3.0, "max": 3.0, "mean": 3.0, "count": 10}], "1969": [{"min": 8.0, "max": 9.0, "mean": 8.3, "count": 10}], "1970": [{"min": 3.0, "max": 3.0, "mean": 3.0, "count": 10}], "1971": [{"min": 11.0, "max": 11.0, "mean": 11.0, "count": 10}], "1972": [{"min": 6.0, "max": 6.0, "mean": 6.0, "count": 10}], "1973": [{"min": 7.0, "max": 7.0, "mean": 7.0, "count": 10}], "1974": [{"min": 5.0, "max": 5.0, "mean": 5.0, "count": 10}], "1975": [{"min": 8.0, "max": 8.0, "mean": 8.0, "count": 10}], "1976": [{"min": 11.0, "max": 11.0, "mean": 11.0, "count": 10}], "1977": [{"min": 3.0, "max": 3.0, "mean": 3.0, "count": 10}], "1978": [{"min": 4.0, "max": 4.0, "mean": 4.0, "count": 10}], "1979": [{"min": 4.0, "max": 5.0, "mean": 4.5, "count": 10}], "1980": [{"min": 3.0, "max": 4.0, "mean": 3.8, "count": 10}], "1981": [{"min": 3.0, "max": 3.0, "mean": 3.0, "count": 10}], "1982": [{"min": 7.0, "max": 7.0, "mean": 7.0, "count": 10}], "1983": [{"min": 9.0, "max": 9.0, "mean": 9.0, "count": 10}], "1984": [{"min": 5.0, "max": 5.0, "mean": 5.0, "count": 10}], "1985": [{"min": 4.0, "max": 4.0, "mean": 4.0, "count": 10}], "1986": [{"min": 6.0, "max": 6.0, "mean": 6.0, "count": 10}], "1987": [{"min": 3.0, "max": 3.0, "mean": 3.0, "count": 10}], "1988": [{"min": 4.0, "max": 5.0, "mean": 4.5, "count": 10}], "1989": [{"min": 7.0, "max": 7.0, "mean": 7.0, "count": 10}], "1990": [{"min": 8.0, "max": 9.0, "mean": 8.3, "count": 10}], "1991": [{"min": 7.0, "max": 7.0, "mean": 7.0, "count": 10}], "1992": [{"min": 11.0, "max": 11.0, "mean": 11.0, "count": 10}], "1993": [{"min": 2.0, "max": 2.0, "mean": 2.0, "count": 10}], "1994": [{"min": 19.0, "max": 20.0, "mean": 19.7, "count": 10}], "1995": [{"min": 11.0, "max": 11.0, "mean": 11.0, "count": 10}], "1996": [{"min": 4.0, "max": 4.0, "mean": 4.0, "count": 10}], "1997": [{"min": 5.0, "max": 5.0, "mean": 5.0, "count": 10}], "1998": [{"min": 9.0, "max": 9.0, "mean": 9.0, "count": 10}], "1999": [{"min": 5.0, "max": 6.0, "mean": 5.7, "count": 10}], "2000": [{"min": 7.0, "max": 7.0, "mean": 7.0, "count": 10}], "2001": [{"min": 9.0, "max": 10.0, "mean": 9.7, "count": 10}], "2002": [{"min": 9.0, "max": 9.0, "mean": 9.0, "count": 10}], "2003": [{"min": 24.0, "max": 25.0, "mean": 24.6, "count": 10}], "2004": [{"min": 6.0, "max": 6.0, "mean": 6.0, "count": 10}], "2005": [{"min": 11.0, "max": 11.0, "mean": 11.0, "count": 10}], "2006": [{"min": 18.0, "max": 19.0, "mean": 18.1, "count": 10}], "2007": [{"min": 7.0, "max": 7.0, "mean": 7.0, "count": 10}], "2008": [{"min": 11.0, "max": 11.0, "mean": 11.0, "count": 10}], "2009": [{"min": 5.0, "max": 5.0, "mean": 5.0, "count": 10}], "2010": [{"min": 11.0, "max": 11.0, "mean": 11.0, "count": 10}], "2011": [{"min": 6.0, "max": 7.0, "mean": 6.7, "count": 10}], "2012": [{"min": 10.0, "max": 10.0, "mean": 10.0, "count": 10}], "2013": [{"min": 14.0, "max": 14.0, "mean": 14.0, "count": 10}], "2014": [{"min": 8.0, "max": 8.0, "mean": 8.0, "count": 10}], "2015": [{"min": 21.0, "max": 21.0, "mean": 21.0, "count": 10}], "2016": [{"min": 16.0, "max": 17.0, "mean": 16.7, "count": 10}], "2017": [{"min": 7.0, "max": 8.0, "mean": 7.9, "count": 10}], "2018": [{"min": 29.0, "max": 32.0, "mean": 31.0, "count": 10}], "2019": [{"min": 22.0, "max": 23.0, "mean": 22.8, "count": 10}], "2020": [{"min": 13.0, "max": 14.0, "mean": 13.7, "count": 10}], "2021": [{"min": 4.0, "max": 5.0, "mean": 4.8, "count": 10}], "2022": [{"min": 21.0, "max": 22.0, "mean": 21.7, "count": 10}], "2023": [{"min": 12.0, "max": 13.0, "mean": 12.8, "count": 10}], "2024": [{"min": 21.0, "max": 22.0, "mean": 21.2, "count": 10}], "2025": [{"min": 14.0, "max": 14.0, "mean": 14.0, "count": 10}]}, "ice_days": {"1951": [{"min": 6.0, "max": 7.0, "mean": 6.5, "count": 10}], "1952": [{"min": 23.0, "max": 26.0, "mean": 23.9, "count": 10}], "1953": [{"min": 19.0, "max": 22.0, "mean": 20.6, "count": 10}], "1954": [{"min": 30.0, "max": 32.0, "mean": 30.7, "count": 10}], "1955": [{"min": 31.0, "max": 33.0, "mean": 31.7, "count": 10}], "1956": [{"min": 43.0, "max": 45.0, "mean": 43.7, "count": 10}], "1957": [{"min": 8.0, "max": 10.0, "mean": 8.8, "count": 10}], "1958": [{"min": 10.0, "max": 13.0, "mean": 10.9, "count": 10}], "1959": [{"min": 17.0, "max": 19.0, "mean": 17.8, "count": 10}], "1960": [{"min": 18.0, "max": 20.0, "mean": 18.8, "count": 10}], "1961": [{"min": 17.0, "max": 19.0, "mean": 17.7, "count": 10}], "1962": [{"min": 29.0, "max": 31.0, "mean": 29.7, "count": 10}], "1963": [{"min": 64.0, "max": 66.0, "mean": 64.7, "count": 10}], "1964": [{"min": 30.0, "max": 33.0, "mean": 31.2, "count": 10}], "1965": [{"min": 25.0, "max": 27.0, "mean": 25.4, "count": 10}], "1966": [{"min": 23.0, "max": 25.0, "mean": 23.6, "count": 10}], "1967": [{"min": 12.0, "max": 14.0, "mean": 12.6, "count": 10}], "1968": [{"min": 33.0, "max": 35.0, "mean": 33.7, "count": 10}], "1969": [{"min": 49.0, "max": 51.0, "mean": 49.7, "count": 10}], "1970": [{"min": 36.0, "max": 38.0, "mean": 36.7, "count": 10}], "1971": [{"min": 17.0, "max": 19.0, "mean": 17.7, "count": 10}], "1972": [{"min": 20.0, "max": 22.0, "mean": 20.7, "count": 10}], "1973": [{"min": 14.0, "max": 16.0, "mean": 14.7, "count": 10}], "1974": [{"min": 0.0, "max": 0.0, "mean": 0.0, "count": 10}], "1975": [{"min": 4.0, "max": 6.0, "mean": 4.7, "count": 10}], "1976": [{"min": 25.0, "max": 27.0, "mean": 25.7, "count": 10}], "1977": [{"min": 8.0, "max": 11.0, "mean": 9.4, "count": 10}], "1978": [{"min": 24.0, "max": 27.0, "mean": 25.0, "count": 10}], "1979": [{"min": 27.0, "max": 29.0, "mean": 27.7, "count": 10}], "1980": [{"min": 29.0, "max": 32.0, "mean": 30.1, "count": 10}], "1981": [{"min": 36.0, "max": 38.0, "mean": 36.7, "count": 10}], "1982": [{"min": 13.0, "max": 15.0, "mean": 13.7, "count": 10}], "1983": [{"min": 19.0, "max": 21.0, "mean": 19.7, "count": 10}], "1984": [{"min": 15.0, "max": 17.0, "mean": 15.7, "count": 10}], "1985": [{"min": 45.0, "max": 47.0, "mean": 45.6, "count": 10}], "1986": [{"min": 37.0, "max": 39.0, "mean": 37.7, "count": 10}], "1987": [{"min": 45.0, "max": 48.0, "mean": 46.2, "count": 10}], "1988": [{"min": 4.0, "max": 7.0, "mean": 5.0, "count": 10}], "1989": [{"min": 3.0, "max": 5.0, "mean": 3.6, "count": 10}], "1990": [{"min": 5.0, "max": 7.0, "mean": 5.7, "count": 10}], "1991": [{"min": 20.0, "max": 22.0, "mean": 20.6, "count": 10}], "1992": [{"min": 12.0, "max": 14.0, "mean": 12.7, "count": 10}], "1993": [{"min": 28.0, "max": 31.0, "mean": 29.2, "count": 10}], "1994": [{"min": 8.0, "max": 10.0, "mean": 8.7, "count": 10}], "1995": [{"min": 26.0, "max": 28.0, "mean": 26.7, "count": 10}], "1996": [{"min": 48.0, "max": 51.0, "mean": 49.4, "count": 10}], "1997": [{"min": 13.0, "max": 15.0, "mean": 13.7, "count": 10}], "1998": [{"min": 18.0, "max": 20.0, "mean": 18.7, "count": 10}], "1999": [{"min": 9.0, "max": 11.0, "mean": 9.7, "count": 10}], "2000": [{"min": 4.0, "max": 6.0, "mean": 4.6, "count": 10}], "2001": [{"min": 15.0, "max": 17.0, "mean": 15.7, "count": 10}], "2002": [{"min": 15.0, "max": 16.0, "mean": 15.5, "count": 10}], "2003": [{"min": 20.0, "max": 22.0, "mean": 20.7, "count": 10}], "2004": [{"min": 10.0, "max": 12.0, "mean": 10.7, "count": 10}], "2005": [{"min": 21.0, "max": 23.0, "mean": 21.7, "count": 10}], "2006": [{"min": 24.0, "max": 26.0, "mean": 25.3, "count": 10}], "2007": [{"min": 10.0, "max": 12.0, "mean": 11.0, "count": 10}], "2008": [{"min": 6.0, "max": 7.0, "mean": 6.5, "count": 10}], "2009": [{"min": 23.0, "max": 25.0, "mean": 23.7, "count": 10}], "2010": [{"min": 58.0, "max": 60.0, "mean": 58.7, "count": 10}], "2011": [{"min": 14.0, "max": 16.0, "mean": 15.2, "count": 10}], "2012": [{"min": 17.0, "max": 19.0, "mean": 17.7, "count": 10}], "2013": [{"min": 31.0, "max": 33.0, "mean": 31.7, "count": 10}], "2014": [{"min": 8.0, "max": 10.0, "mean": 9.2, "count": 10}], "2015": [{"min": 0.0, "max": 3.0, "mean": 1.5, "count": 10}], "2016": [{"min": 9.0, "max": 11.0, "mean": 10.2, "count": 10}], "2017": [{"min": 14.0, "max": 15.0, "mean": 14.5, "count": 10}], "2018": [{"min": 12.0, "max": 14.0, "mean": 12.7, "count": 10}], "2019": [{"min": 3.0, "max": 5.0, "mean": 4.2, "count": 10}], "2020": [{"min": 0.0, "max": 0.0, "mean": 0.0, "count": 10}], "2021": [{"min": 12.0, "max": 13.0, "mean": 12.5, "count": 10}], "2022": [{"min": 6.0, "max": 8.0, "mean": 7.2, "count": 10}], "2023": [{"min": 4.0, "max": 6.0, "mean": 4.7, "count": 10}], "2024": [{"min": 4.0, "max": 6.0, "mean": 5.2, "count": 10}], "2025": [{"min": 4.0, "max": 6.0, "mean": 5.4, "count": 10}]}, "precipGE10mm_days": {"1951": [{"min": 12.0, "max": 13.0, "mean": 12.6, "count": 10}], "1952": [{"min": 12.0, "max": 13.0, "mean": 12.7, "count": 10}], "1953": [{"min": 9.0, "max": 11.0, "mean": 10.3, "count": 10}], "1954": [{"min": 13.0, "max": 14.0, "mean": 13.7, "count": 10}], "1955": [{"min": 12.0, "max": 14.0, "mean": 13.3, "count": 10}], "1956": [{"min": 15.0, "max": 16.0, "mean": 15.7, "count": 10}], "1957": [{"min": 9.0, "max": 11.0, "mean": 10.3, "count": 10}], "1958": [{"min": 15.0, "max": 17.0, "mean": 16.1, "count": 10}], "1959": [{"min": 8.0, "max": 9.0, "mean": 8.7, "count": 10}], "1960": [{"min": 14.0, "max": 15.0, "mean": 14.7, "count": 10}], "1961": [{"min": 11.0, "max": 13.0, "mean": 12.4, "count": 10}], "1962": [{"min": 6.0, "max": 7.0, "mean": 6.7, "count": 10}], "1963": [{"min": 8.0, "max": 9.0, "mean": 8.7, "count": 10}], "1964": [{"min": 6.0, "max": 8.0, "mean": 6.9, "count": 10}], "1965": [{"min": 15.0, "max": 16.0, "mean": 15.7, "count": 10}], "1966": [{"min": 17.0, "max": 19.0, "mean": 18.3, "count": 10}], "1967": [{"min": 9.0, "max": 10.0, "mean": 9.7, "count": 10}], "1968": [{"min": 9.0, "max": 10.0, "mean": 9.7, "count": 10}], "1969": [{"min": 11.0, "max": 12.0, "mean": 11.7, "count": 10}], "1970": [{"min": 12.0, "max": 14.0, "mean": 13.4, "count": 10}], "1971": [{"min": 8.0, "max": 9.0, "mean": 8.7, "count": 10}], "1972": [{"min": 15.0, "max": 16.0, "mean": 15.7, "count": 10}], "1973": [{"min": 8.0, "max": 9.0, "mean": 8.7, "count": 10}], "1974": [{"min": 12.0, "max": 14.0, "mean": 13.4, "count": 10}], "1975": [{"min": 9.0, "max": 10.0, "mean": 9.7, "count": 10}], "1976": [{"min": 5.0, "max": 7.0, "mean": 6.2, "count": 10}], "1977": [{"min": 22.0, "max": 23.0, "mean": 22.6, "count": 10}], "1978": [{"min": 10.0, "max": 11.0, "mean": 10.5, "count": 10}], "1979": [{"min": 10.0, "max": 11.0, "mean": 10.7, "count": 10}], "1980": [{"min": 10.0, "max": 12.0, "mean": 11.2, "count": 10}], "1981": [{"min": 16.0, "max": 18.0, "mean": 16.7, "count": 10}], "1982": [{"min": 5.0, "max": 6.0, "mean": 5.6, "count": 10}], "1983": [{"min": 12.0, "max": 14.0, "mean": 13.4, "count": 10}], "1984": [{"min": 14.0, "max": 16.0, "mean": 15.2, "count": 10}], "1985": [{"min": 8.0, "max": 10.0, "mean": 9.4, "count": 10}], "1986": [{"min": 12.0, "max": 14.0, "mean": 12.9, "count": 10}], "1987": [{"min": 16.0, "max": 17.0, "mean": 16.5, "count": 10}], "1988": [{"min": 6.0, "max": 8.0, "mean": 7.4, "count": 10}], "1989": [{"min": 7.0, "max": 9.0, "mean": 7.9, "count": 10}], "1990": [{"min": 6.0, "max": 8.0, "mean": 6.6, "count": 10}], "1991": [{"min": 3.0, "max": 5.0, "mean": 4.2, "count": 10}], "1992": [{"min": 10.0, "max": 12.0, "mean": 11.3, "count": 10}], "1993": [{"min": 13.0, "max": 14.0, "mean": 13.7, "count": 10}], "1994": [{"min": 14.0, "max": 15.0, "mean": 14.7, "count": 10}], "1995": [{"min": 13.0, "max": 15.0, "mean": 14.1, "count": 10}], "1996": [{"min": 12.0, "max": 13.0, "mean": 12.6, "count": 10}], "1997": [{"min": 9.0, "max": 11.0, "mean": 10.4, "count": 10}], "1998": [{"min": 11.0, "max": 13.0, "mean": 11.8, "count": 10}], "1999": [{"min": 10.0, "max": 11.0, "mean": 10.6, "count": 10}], "2000": [{"min": 9.0, "max": 10.0, "mean": 9.7, "count": 10}], "2001": [{"min": 11.0, "max": 13.0, "mean": 11.8, "count": 10}], "2002": [{"min": 17.0, "max": 19.0, "mean": 18.2, "count": 10}], "2003": [{"min": 8.0, "max": 9.0, "mean": 8.6, "count": 10}], "2004": [{"min": 11.0, "max": 13.0, "mean": 11.9, "count": 10}], "2005": [{"min": 10.0, "max": 13.0, "mean": 11.4, "count": 10}], "2006": [{"min": 8.0, "max": 9.0, "mean": 8.7, "count": 10}], "2007": [{"min": 17.0, "max": 18.0, "mean": 17.7, "count": 10}], "2008": [{"min": 10.0, "max": 11.0, "mean": 10.5, "count": 10}], "2009": [{"min": 13.0, "max": 15.0, "mean": 14.4, "count": 10}], "2010": [{"min": 16.0, "max": 17.0, "mean": 16.6, "count": 10}], "2011": [{"min": 8.0, "max": 9.0, "mean": 8.5, "count": 10}], "2012": [{"min": 7.0, "max": 9.0, "mean": 7.8, "count": 10}], "2013": [{"min": 9.0, "max": 11.0, "mean": 9.9, "count": 10}], "2014": [{"min": 8.0, "max": 9.0, "mean": 8.7, "count": 10}], "2015": [{"min": 7.0, "max": 9.0, "mean": 8.2, "count": 10}], "2016": [{"min": 8.0, "max": 10.0, "mean": 9.2, "count": 10}], "2017": [{"min": 11.0, "max": 12.0, "mean": 11.7, "count": 10}], "2018": [{"min": 4.0, "max": 5.0, "mean": 4.7, "count": 10}], "2019": [{"min": 6.0, "max": 8.0, "mean": 6.9, "count": 10}], "2020": [{"min": 12.0, "max": 14.0, "mean": 12.7, "count": 10}], "2021": [{"min": 12.0, "max": 14.0, "mean": 12.8, "count": 10}], "2022": [{"min": 6.0, "max": 7.0, "mean": 6.7, "count": 10}], "2023": [{"min": 13.0, "max": 14.0, "mean": 13.5, "count": 10}], "2024": [{"min": 13.0, "max": 15.0, "mean": 14.2, "count": 10}], "2025": [{"min": 7.0, "max": 8.0, "mean": 7.5, "count": 10}]}, "precipGE20mm_days": {"1951": [{"min": 4.0, "max": 4.0, "mean": 4.0, "count": 10}], "1952": [{"min": 2.0, "max": 2.0, "mean": 2.0, "count": 10}], "1953": [{"min": 3.0, "max": 3.0, "mean": 3.0, "count": 10}], "1954": [{"min": 3.0, "max": 4.0, "mean": 3.7, "count": 10}], "1955": [{"min": 4.0, "max": 4.0, "mean": 4.0, "count": 10}], "1956": [{"min": 5.0, "max": 5.0, "mean": 5.0, "count": 10}], "1957": [{"min": 3.0, "max": 3.0, "mean": 3.0, "count": 10}], "1958": [{"min": 4.0, "max": 4.0, "mean": 4.0, "count": 10}], "1959": [{"min": 4.0, "max": 4.0, "mean": 4.0, "count": 10}], "1960": [{"min": 3.0, "max": 4.0, "mean": 3.3, "count": 10}], "1961": [{"min": 5.0, "max": 5.0, "mean": 5.0, "count": 10}], "1962": [{"min": 1.0, "max": 1.0, "mean": 1.0, "count": 10}], "1963": [{"min": 2.0, "max": 3.0, "mean": 2.8, "count": 10}], "1964": [{"min": 2.0, "max": 2.0, "mean": 2.0, "count": 10}], "1965": [{"min": 4.0, "max": 4.0, "mean": 4.0, "count": 10}], "1966": [{"min": 4.0, "max": 4.0, "mean": 4.0, "count": 10}], "1967": [{"min": 3.0, "max": 3.0, "mean": 3.0, "count": 10}], "1968": [{"min": 4.0, "max": 4.0, "mean": 4.0, "count": 10}], "1969": [{"min": 2.0, "max": 2.0, "mean": 2.0, "count": 10}], "1970": [{"min": 3.0, "max": 3.0, "mean": 3.0, "count": 10}], "1971": [{"min": 2.0, "max": 2.0, "mean": 2.0, "count": 10}], "1972": [{"min": 4.0, "max": 5.0, "mean": 4.7, "count": 10}], "1973": [{"min": 2.0, "max": 2.0, "mean": 2.0, "count": 10}], "1974": [{"min": 2.0, "max": 2.0, "mean": 2.0, "count": 10}], "1975": [{"min": 3.0, "max": 3.0, "mean": 3.0, "count": 10}], "1976": [{"min": 2.0, "max": 2.0, "mean": 2.0, "count": 10}], "1977": [{"min": 5.0, "max": 5.0, "mean": 5.0, "count": 10}], "1978": [{"min": 2.0, "max": 2.0, "mean": 2.0, "count": 10}], "1979": [{"min": 2.0, "max": 2.0, "mean": 2.0, "count": 10}], "1980": [{"min": 2.0, "max": 3.0, "mean": 2.8, "count": 10}], "1981": [{"min": 5.0, "max": 5.0, "mean": 5.0, "count": 10}], "1982": [{"min": 1.0, "max": 2.0, "mean": 1.9, "count": 10}], "1983": [{"min": 4.0, "max": 5.0, "mean": 4.8, "count": 10}], "1984": [{"min": 4.0, "max": 4.0, "mean": 4.0, "count": 10}], "1985": [{"min": 1.0, "max": 1.0, "mean": 1.0, "count": 10}], "1986": [{"min": 2.0, "max": 3.0, "mean": 2.3, "count": 10}], "1987": [{"min": 3.0, "max": 4.0, "mean": 3.5, "count": 10}], "1988": [{"min": 2.0, "max": 2.0, "mean": 2.0, "count": 10}], "1989": [{"min": 1.0, "max": 1.0, "mean": 1.0, "count": 10}], "1990": [{"min": 2.0, "max": 2.0, "mean": 2.0, "count": 10}], "1991": [{"min": 1.0, "max": 1.0, "mean": 1.0, "count": 10}], "1992": [{"min": 3.0, "max": 4.0, "mean": 3.9, "count": 10}], "1993": [{"min": 3.0, "max": 3.0, "mean": 3.0, "count": 10}], "1994": [{"min": 3.0, "max": 3.0, "mean": 3.0, "count": 10}], "1995": [{"min": 4.0, "max": 5.0, "mean": 4.4, "count": 10}], "1996": [{"min": 4.0, "max": 4.0, "mean": 4.0, "count": 10}], "1997": [{"min": 3.0, "max": 3.0, "mean": 3.0, "count": 10}], "1998": [{"min": 2.0, "max": 2.0, "mean": 2.0, "count": 10}], "1999": [{"min": 3.0, "max": 3.0, "mean": 3.0, "count": 10}], "2000": [{"min": 1.0, "max": 1.0, "mean": 1.0, "count": 10}], "2001": [{"min": 1.0, "max": 2.0, "mean": 1.5, "count": 10}], "2002": [{"min": 5.0, "max": 6.0, "mean": 5.9, "count": 10}], "2003": [{"min": 3.0, "max": 4.0, "mean": 3.1, "count": 10}], "2004": [{"min": 4.0, "max": 5.0, "mean": 4.4, "count": 10}], "2005": [{"min": 2.0, "max": 3.0, "mean": 2.1, "count": 10}], "2006": [{"min": 1.0, "max": 1.0, "mean": 1.0, "count": 10}], "2007": [{"min": 8.0, "max": 8.0, "mean": 8.0, "count": 10}], "2008": [{"min": 3.0, "max": 4.0, "mean": 3.8, "count": 10}], "2009": [{"min": 3.0, "max": 4.0, "mean": 3.2, "count": 10}], "2010": [{"min": 4.0, "max": 4.0, "mean": 4.0, "count": 10}], "2011": [{"min": 3.0, "max": 3.0, "mean": 3.0, "count": 10}], "2012": [{"min": 3.0, "max": 3.0, "mean": 3.0, "count": 10}], "2013": [{"min": 5.0, "max": 5.0, "mean": 5.0, "count": 10}], "2014": [{"min": 5.0, "max": 5.0, "mean": 5.0, "count": 10}], "2015": [{"min": 2.0, "max": 2.0, "mean": 2.0, "count": 10}], "2016": [{"min": 3.0, "max": 3.0, "mean": 3.0, "count": 10}], "2017": [{"min": 5.0, "max": 5.0, "mean": 5.0, "count": 10}], "2018": [{"min": 2.0, "max": 3.0, "mean": 2.8, "count": 10}], "2019": [{"min": 2.0, "max": 3.0, "mean": 2.8, "count": 10}], "2020": [{"min": 5.0, "max": 5.0, "mean": 5.0, "count": 10}], "2021": [{"min": 5.0, "max": 6.0, "mean": 5.4, "count": 10}], "2022": [{"min": 2.0, "max": 3.0, "mean": 2.4, "count": 10}], "2023": [{"min": 4.0, "max": 4.0, "mean": 4.0, "count": 10}], "2024": [{"min": 4.0, "max": 4.0, "mean": 4.0, "count": 10}], "2025": [{"min": 4.0, "max": 4.0, "mean": 4.0, "count": 10}]}, "precipGE30mm_days": {"1951": [{"min": 1.0, "max": 1.0, "mean": 1.0, "count": 10}], "1952": [{"min": 1.0, "max": 1.0, "mean": 1.0, "count": 10}], "1953": [{"min": 1.0, "max": 1.0, "mean": 1.0, "count": 10}], "1954": [{"min": 1.0, "max": 1.0, "mean": 1.0, "count": 10}], "1955": [{"min": 1.0, "max": 1.0, "mean": 1.0, "count": 10}], "1956": [{"min": 2.0, "max": 2.0, "mean": 2.0, "count": 10}], "1957": [{"min": 0.0, "max": 1.0, "mean": 0.5, "count": 10}], "1958": [{"min": 2.0, "max": 2.0, "mean": 2.0, "count": 10}], "1959": [{"min": 1.0, "max": 1.0, "mean": 1.0, "count": 10}], "1960": [{"min": 1.0, "max": 1.0, "mean": 1.0, "count": 10}], "1961": [{"min": 2.0, "max": 2.0, "mean": 2.0, "count": 10}], "1962": [{"min": 0.0, "max": 0.0, "mean": 0.0, "count": 10}], "1963": [{"min": 0.0, "max": 0.0, "mean": 0.0, "count": 10}], "1964": [{"min": 1.0, "max": 1.0, "mean": 1.0, "count": 10}], "1965": [{"min": 1.0, "max": 1.0, "mean": 1.0, "count": 10}], "1966": [{"min": 1.0, "max": 1.0, "mean": 1.0, "count": 10}], "1967": [{"min": 1.0, "max": 1.0, "mean": 1.0, "count": 10}], "1968": [{"min": 1.0, "max": 1.0, "mean": 1.0, "count": 10}], "1969": [{"min": 0.0, "max": 0.0, "mean": 0.0, "count": 10}], "1970": [{"min": 1.0, "max": 1.0, "mean": 1.0, "count": 10}], "1971": [{"min": 1.0, "max": 1.0, "mean": 1.0, "count": 10}], "1972": [{"min": 1.0, "max": 1.0, "mean": 1.0, "count": 10}], "1973": [{"min": 0.0, "max": 0.0, "mean": 0.0, "count": 10}], "1974": [{"min": 1.0, "max": 1.0, "mean": 1.0, "count": 10}], "1975": [{"min": 1.0, "max": 1.0, "mean": 1.0, "count": 10}], "1976": [{"min": 0.0, "max": 0.0, "mean": 0.0, "count": 10}], "1977": [{"min": 2.0, "max": 2.0, "mean": 2.0, "count": 10}], "1978": [{"min": 0.0, "max": 1.0, "mean": 0.5, "count": 10}], "1979": [{"min": 0.0, "max": 0.0, "mean": 0.0, "count": 10}], "1980": [{"min": 1.0, "max": 1.0, "mean": 1.0, "count": 10}], "1981": [{"min": 3.0, "max": 3.0, "mean": 3.0, "count": 10}], "1982": [{"min": 0.0, "max": 0.0, "mean": 0.0, "count": 10}], "1983": [{"min": 1.0, "max": 2.0, "mean": 1.1, "count": 10}], "1984": [{"min": 2.0, "max": 2.0, "mean": 2.0, "count": 10}], "1985": [{"min": 0.0, "max": 0.0, "mean": 0.0, "count": 10}], "1986": [{"min": 1.0, "max": 1.0, "mean": 1.0, "count": 10}], "1987": [{"min": 0.0, "max": 0.0, "mean": 0.0, "count": 10}], "1988": [{"min": 0.0, "max": 0.0, "mean": 0.0, "count": 10}], "1989": [{"min": 0.0, "max": 0.0, "mean": 0.0, "count": 10}], "1990": [{"min": 1.0, "max": 1.0, "mean": 1.0, "count": 10}], "1991": [{"min": 0.0, "max": 0.0, "mean": 0.0, "count": 10}], "1992": [{"min": 2.0, "max": 2.0, "mean": 2.0, "count": 10}], "1993": [{"min": 1.0, "max": 1.0, "mean": 1.0, "count": 10}], "1994": [{"min": 2.0, "max": 2.0, "mean": 2.0, "count": 10}], "1995": [{"min": 2.0, "max": 2.0, "mean": 2.0, "count": 10}], "1996": [{"min": 1.0, "max": 1.0, "mean": 1.0, "count": 10}], "1997": [{"min": 1.0, "max": 2.0, "mean": 1.5, "count": 10}], "1998": [{"min": 0.0, "max": 0.0, "mean": 0.0, "count": 10}], "1999": [{"min": 1.0, "max": 1.0, "mean": 1.0, "count": 10}], "2000": [{"min": 0.0, "max": 0.0, "mean": 0.0, "count": 10}], "2001": [{"min": 0.0, "max": 0.0, "mean": 0.0, "count": 10}], "2002": [{"min": 1.0, "max": 2.0, "mean": 1.9, "count": 10}], "2003": [{"min": 0.0, "max": 1.0, "mean": 0.1, "count": 10}], "2004": [{"min": 2.0, "max": 2.0, "mean": 2.0, "count": 10}], "2005": [{"min": 1.0, "max": 1.0, "mean": 1.0, "count": 10}], "2006": [{"min": 0.0, "max": 0.0, "mean": 0.0, "count": 10}], "2007": [{"min": 3.0, "max": 4.0, "mean": 3.4, "count": 10}], "2008": [{"min": 1.0, "max": 1.0, "mean": 1.0, "count": 10}], "2009": [{"min": 0.0, "max": 0.0, "mean": 0.0, "count": 10}], "2010": [{"min": 2.0, "max": 2.0, "mean": 2.0, "count": 10}], "2011": [{"min": 1.0, "max": 1.0, "mean": 1.0, "count": 10}], "2012": [{"min": 0.0, "max": 0.0, "mean": 0.0, "count": 10}], "2013": [{"min": 2.0, "max": 2.0, "mean": 2.0, "count": 10}], "2014": [{"min": 2.0, "max": 2.0, "mean": 2.0, "count": 10}], "2015": [{"min": 1.0, "max": 1.0, "mean": 1.0, "count": 10}], "2016": [{"min": 1.0, "max": 1.0, "mean": 1.0, "count": 10}], "2017": [{"min": 1.0, "max": 2.0, "mean": 1.3, "count": 10}], "2018": [{"min": 1.0, "max": 1.0, "mean": 1.0, "count": 10}], "2019": [{"min": 0.0, "max": 1.0, "mean": 0.9, "count": 10}], "2020": [{"min": 1.0, "max": 1.0, "mean": 1.0, "count": 10}], "2021": [{"min": 3.0, "max": 3.0, "mean": 3.0, "count": 10}], "2022": [{"min": 1.0, "max": 1.0, "mean": 1.0, "count": 10}], "2023": [{"min": 1.0, "max": 1.0, "mean": 1.0, "count": 10}], "2024": [{"min": 2.0, "max": 2.0, "mean": 2.0, "count": 10}], "2025": [{"min": 2.0, "max": 2.0, "mean": 2.0, "count": 10}]}, "precipitation": {"1881": [{"min": 472.0, "max": 495.0, "mean": 483.4, "count": 10}], "1882": [{"min": 650.0, "max": 680.0, "mean": 664.4, "count": 10}], "1883": [{"min": 432.0, "max": 450.0, "mean": 440.6, "count": 10}], "1884": [{"min": 518.0, "max": 545.0, "mean": 532.6, "count": 10}], "1885": [{"min": 457.0, "max": 476.0, "mean": 466.4, "count": 10}], "1886": [{"min": 478.0, "max": 503.0, "mean": 489.2, "count": 10}], "1887": [{"min": 422.0, "max": 439.0, "mean": 430.0, "count": 10}], "1888": [{"min": 500.0, "max": 522.0, "mean": 510.5, "count": 10}], "1889": [{"min": 528.0, "max": 550.0, "mean": 538.5, "count": 10}], "1890": [{"min": 503.0, "max": 524.0, "mean": 512.7, "count": 10}], "1891": [{"min": 529.0, "max": 553.0, "mean": 540.0, "count": 10}], "1892": [{"min": 348.0, "max": 371.0, "mean": 357.8, "count": 10}], "1893": [{"min": 496.0, "max": 519.0, "mean": 506.6, "count": 10}], "1894": [{"min": 539.0, "max": 563.0, "mean": 549.3, "count": 10}], "1895": [{"min": 525.0, "max": 552.0, "mean": 537.0, "count": 10}], "1896": [{"min": 535.0, "max": 555.0, "mean": 545.5, "count": 10}], "1897": [{"min": 573.0, "max": 602.0, "mean": 586.6, "count": 10}], "1898": [{"min": 556.0, "max": 589.0, "mean": 572.2, "count": 10}], "1899": [{"min": 553.0, "max": 576.0, "mean": 563.4, "count": 10}], "1900": [{"min": 591.0, "max": 614.0, "mean": 601.8, "count": 10}], "1901": [{"min": 590.0, "max": 620.0, "mean": 603.2, "count": 10}], "1902": [{"min": 492.0, "max": 513.0, "mean": 499.9, "count": 10}], "1903": [{"min": 443.0, "max": 460.0, "mean": 451.7, "count": 10}], "1904": [{"min": 402.0, "max": 424.0, "mean": 411.4, "count": 10}], "1905": [{"min": 589.0, "max": 617.0, "mean": 601.7, "count": 10}], "1906": [{"min": 620.0, "max": 648.0, "mean": 632.1, "count": 10}], "1907": [{"min": 480.0, "max": 499.0, "mean": 488.0, "count": 10}], "1908": [{"min": 456.0, "max": 472.0, "mean": 463.4, "count": 10}], "1909": [{"min": 587.0, "max": 618.0, "mean": 600.4, "count": 10}], "1910": [{"min": 484.0, "max": 504.0, "mean": 492.9, "count": 10}], "1911": [{"min": 301.0, "max": 318.0, "mean": 308.2, "count": 10}], "1912": [{"min": 554.0, "max": 584.0, "mean": 567.3, "count": 10}], "1913": [{"min": 446.0, "max": 470.0, "mean": 456.3, "count": 10}], "1914": [{"min": 538.0, "max": 559.0, "mean": 547.6, "count": 10}], "1915": [{"min": 474.0, "max": 503.0, "mean": 484.8, "count": 10}], "1916": [{"min": 485.0, "max": 526.0, "mean": 506.1, "count": 10}], "1917": [{"min": 505.0, "max": 530.0, "mean": 515.8, "count": 10}], "1918": [{"min": 473.0, "max": 497.0, "mean": 484.1, "count": 10}], "1919": [{"min": 412.0, "max": 442.0, "mean": 425.2, "count": 10}], "1920": [{"min": 472.0, "max": 496.0, "mean": 483.5, "count": 10}], "1921": [{"min": 420.0, "max": 440.0, "mean": 428.5, "count": 10}], "1922": [{"min": 584.0, "max": 610.0, "mean": 597.3, "count": 10}], "1923": [{"min": 503.0, "max": 535.0, "mean": 517.8, "count": 10}], "1924": [{"min": 572.0, "max": 594.0, "mean": 583.8, "count": 10}], "1925": [{"min": 502.0, "max": 523.0, "mean": 512.4, "count": 10}], "1926": [{"min": 599.0, "max": 626.0, "mean": 611.7, "count": 10}], "1927": [{"min": 559.0, "max": 582.0, "mean": 568.9, "count": 10}], "1928": [{"min": 462.0, "max": 487.0, "mean": 473.9, "count": 10}], "1929": [{"min": 408.0, "max": 429.0, "mean": 416.6, "count": 10}], "1930": [{"min": 530.0, "max": 549.0, "mean": 539.8, "count": 10}], "1931": [{"min": 497.0, "max": 532.0, "mean": 513.6, "count": 10}], "1932": [{"min": 459.0, "max": 482.0, "mean": 468.6, "count": 10}], "1933": [{"min": 432.0, "max": 455.0, "mean": 441.9, "count": 10}], "1934": [{"min": 373.0, "max": 391.0, "mean": 381.5, "count": 10}], "1935": [{"min": 482.0, "max": 505.0, "mean": 493.6, "count": 10}], "1936": [{"min": 535.0, "max": 562.0, "mean": 544.6, "count": 10}], "1937": [{"min": 537.0, "max": 561.0, "mean": 547.5, "count": 10}], "1938": [{"min": 451.0, "max": 475.0, "mean": 464.7, "count": 10}], "1939": [{"min": 682.0, "max": 712.0, "mean": 699.5, "count": 10}], "1940": [{"min": 578.0, "max": 603.0, "mean": 591.5, "count": 10}], "1941": [{"min": 642.0, "max": 672.0, "mean": 655.3, "count": 10}], "1942": [{"min": 457.0, "max": 473.0, "mean": 464.6, "count": 10}], "1943": [{"min": 347.0, "max": 363.0, "mean": 352.5, "count": 10}], "1944": [{"min": 541.0, "max": 567.0, "mean": 555.5, "count": 10}], "1945": [{"min": 568.0, "max": 593.0, "mean": 579.3, "count": 10}], "1946": [{"min": 485.0, "max": 509.0, "mean": 495.6, "count": 10}], "1947": [{"min": 428.0, "max": 460.0, "mean": 442.3, "count": 10}], "1948": [{"min": 456.0, "max": 474.0, "mean": 464.0, "count": 10}], "1949": [{"min": 462.0, "max": 484.0, "mean": 472.9, "count": 10}], "1950": [{"min": 629.0, "max": 664.0, "mean": 643.6, "count": 10}], "1951": [{"min": 501.0, "max": 529.0, "mean": 512.8, "count": 10}], "1952": [{"min": 546.0, "max": 578.0, "mean": 562.3, "count": 10}], "1953": [{"min": 422.0, "max": 446.0, "mean": 434.9, "count": 10}], "1954": [{"min": 560.0, "max": 583.0, "mean": 572.1, "count": 10}], "1955": [{"min": 589.0, "max": 624.0, "mean": 606.6, "count": 10}], "1956": [{"min": 662.0, "max": 694.0, "mean": 676.8, "count": 10}], "1957": [{"min": 507.0, "max": 528.0, "mean": 515.9, "count": 10}], "1958": [{"min": 665.0, "max": 688.0, "mean": 675.0, "count": 10}], "1959": [{"min": 347.0, "max": 364.0, "mean": 354.1, "count": 10}], "1960": [{"min": 581.0, "max": 615.0, "mean": 598.9, "count": 10}], "1961": [{"min": 595.0, "max": 628.0, "mean": 609.0, "count": 10}], "1962": [{"min": 403.0, "max": 421.0, "mean": 412.1, "count": 10}], "1963": [{"min": 445.0, "max": 465.0, "mean": 453.3, "count": 10}], "1964": [{"min": 386.0, "max": 410.0, "mean": 397.7, "count": 10}], "1965": [{"min": 618.0, "max": 650.0, "mean": 632.1, "count": 10}], "1966": [{"min": 647.0, "max": 700.0, "mean": 672.8, "count": 10}], "1967": [{"min": 501.0, "max": 528.0, "mean": 516.1, "count": 10}], "1968": [{"min": 505.0, "max": 530.0, "mean": 516.9, "count": 10}], "1969": [{"min": 514.0, "max": 544.0, "mean": 526.5, "count": 10}], "1970": [{"min": 606.0, "max": 642.0, "mean": 624.5, "count": 10}], "1971": [{"min": 400.0, "max": 420.0, "mean": 410.6, "count": 10}], "1972": [{"min": 543.0, "max": 562.0, "mean": 551.7, "count": 10}], "1973": [{"min": 404.0, "max": 425.0, "mean": 414.0, "count": 10}], "1974": [{"min": 608.0, "max": 639.0, "mean": 623.5, "count": 10}], "1975": [{"min": 440.0, "max": 453.0, "mean": 446.9, "count": 10}], "1976": [{"min": 355.0, "max": 371.0, "mean": 363.2, "count": 10}], "1977": [{"min": 671.0, "max": 698.0, "mean": 685.5, "count": 10}], "1978": [{"min": 473.0, "max": 498.0, "mean": 484.0, "count": 10}], "1979": [{"min": 508.0, "max": 536.0, "mean": 522.8, "count": 10}], "1980": [{"min": 530.0, "max": 551.0, "mean": 540.5, "count": 10}], "1981": [{"min": 687.0, "max": 721.0, "mean": 703.5, "count": 10}], "1982": [{"min": 325.0, "max": 340.0, "mean": 332.1, "count": 10}], "1983": [{"min": 536.0, "max": 568.0, "mean": 552.8, "count": 10}], "1984": [{"min": 604.0, "max": 630.0, "mean": 616.7, "count": 10}], "1985": [{"min": 427.0, "max": 446.0, "mean": 435.3, "count": 10}], "1986": [{"min": 532.0, "max": 557.0, "mean": 544.5, "count": 10}], "1987": [{"min": 642.0, "max": 671.0, "mean": 656.4, "count": 10}], "1988": [{"min": 459.0, "max": 491.0, "mean": 477.6, "count": 10}], "1989": [{"min": 415.0, "max": 437.0, "mean": 426.0, "count": 10}], "1990": [{"min": 411.0, "max": 430.0, "mean": 421.6, "count": 10}], "1991": [{"min": 341.0, "max": 355.0, "mean": 346.5, "count": 10}], "1992": [{"min": 547.0, "max": 570.0, "mean": 560.5, "count": 10}], "1993": [{"min": 573.0, "max": 603.0, "mean": 588.6, "count": 10}], "1994": [{"min": 612.0, "max": 639.0, "mean": 627.0, "count": 10}], "1995": [{"min": 600.0, "max": 629.0, "mean": 614.0, "count": 10}], "1996": [{"min": 546.0, "max": 567.0, "mean": 555.1, "count": 10}], "1997": [{"min": 531.0, "max": 551.0, "mean": 541.7, "count": 10}], "1998": [{"min": 552.0, "max": 575.0, "mean": 564.9, "count": 10}], "1999": [{"min": 522.0, "max": 543.0, "mean": 531.2, "count": 10}], "2000": [{"min": 586.0, "max": 610.0, "mean": 596.8, "count": 10}], "2001": [{"min": 576.0, "max": 604.0, "mean": 588.6, "count": 10}], "2002": [{"min": 695.0, "max": 730.0, "mean": 709.8, "count": 10}], "2003": [{"min": 413.0, "max": 434.0, "mean": 424.3, "count": 10}], "2004": [{"min": 544.0, "max": 569.0, "mean": 557.8, "count": 10}], "2005": [{"min": 511.0, "max": 541.0, "mean": 523.0, "count": 10}], "2006": [{"min": 462.0, "max": 487.0, "mean": 474.6, "count": 10}], "2007": [{"min": 728.0, "max": 756.0, "mean": 743.0, "count": 10}], "2008": [{"min": 505.0, "max": 528.0, "mean": 516.7, "count": 10}], "2009": [{"min": 623.0, "max": 654.0, "mean": 637.3, "count": 10}], "2010": [{"min": 643.0, "max": 670.0, "mean": 655.6, "count": 10}], "2011": [{"min": 440.0, "max": 461.0, "mean": 451.3, "count": 10}], "2012": [{"min": 491.0, "max": 515.0, "mean": 502.3, "count": 10}], "2013": [{"min": 552.0, "max": 578.0, "mean": 562.6, "count": 10}], "2014": [{"min": 479.0, "max": 505.0, "mean": 489.6, "count": 10}], "2015": [{"min": 451.0, "max": 473.0, "mean": 462.9, "count": 10}], "2016": [{"min": 439.0, "max": 465.0, "mean": 450.6, "count": 10}], "2017": [{"min": 578.0, "max": 601.0, "mean": 591.2, "count": 10}], "2018": [{"min": 332.0, "max": 349.0, "mean": 340.1, "count": 10}], "2019": [{"min": 417.0, "max": 437.0, "mean": 427.1, "count": 10}], "2020": [{"min": 493.0, "max": 514.0, "mean": 502.9, "count": 10}], "2021": [{"min": 624.0, "max": 650.0, "mean": 638.5, "count": 10}], "2022": [{"min": 419.0, "max": 440.0, "mean": 429.1, "count": 10}], "2023": [{"min": 611.0, "max": 638.0, "mean": 625.6, "count": 10}], "2024": [{"min": 566.0, "max": 596.0, "mean": 581.2, "count": 10}], "2025": [{"min": 432.0, "max": 451.0, "mean": 442.5, "count": 10}]}, "snowcover_days": {"1951": [{"min": 14.0, "max": 20.0, "mean": 16.8, "count": 10}], "1952": [{"min": 39.0, "max": 45.0, "mean": 41.9, "count": 10}], "1953": [{"min": 37.0, "max": 41.0, "mean": 38.9, "count": 10}], "1954": [{"min": 15.0, "max": 21.0, "mean": 18.3, "count": 10}], "1955": [{"min": 58.0, "max": 63.0, "mean": 60.5, "count": 10}], "1956": [{"min": 42.0, "max": 47.0, "mean": 44.4, "count": 10}], "1957": [{"min": 9.0, "max": 13.0, "mean": 10.8, "count": 10}], "1958": [{"min": 31.0, "max": 36.0, "mean": 34.0, "count": 10}], "1959": [{"min": 16.0, "max": 21.0, "mean": 18.7, "count": 10}], "1960": [{"min": 40.0, "max": 44.0, "mean": 41.7, "count": 10}], "1961": [{"min": 23.0, "max": 27.0, "mean": 25.3, "count": 10}], "1962": [{"min": 35.0, "max": 39.0, "mean": 36.8, "count": 10}], "1963": [{"min": 70.0, "max": 74.0, "mean": 72.2, "count": 10}], "1964": [{"min": 34.0, "max": 39.0, "mean": 36.3, "count": 10}], "1965": [{"min": 56.0, "max": 61.0, "mean": 58.3, "count": 10}], "1966": [{"min": 32.0, "max": 36.0, "mean": 33.7, "count": 10}], "1967": [{"min": 13.0, "max": 18.0, "mean": 15.4, "count": 10}], "1968": [{"min": 36.0, "max": 40.0, "mean": 37.7, "count": 10}], "1969": [{"min": 72.0, "max": 77.0, "mean": 74.3, "count": 10}], "1970": [{"min": 71.0, "max": 76.0, "mean": 73.5, "count": 10}], "1971": [{"min": 34.0, "max": 38.0, "mean": 36.0, "count": 10}], "1972": [{"min": 28.0, "max": 33.0, "mean": 30.8, "count": 10}], "1973": [{"min": 21.0, "max": 26.0, "mean": 23.5, "count": 10}], "1974": [{"min": 0.0, "max": 2.0, "mean": 0.3, "count": 10}], "1975": [{"min": 0.0, "max": 3.0, "mean": 0.8, "count": 10}], "1976": [{"min": 33.0, "max": 37.0, "mean": 35.0, "count": 10}], "1977": [{"min": 19.0, "max": 24.0, "mean": 21.3, "count": 10}], "1978": [{"min": 33.0, "max": 38.0, "mean": 35.3, "count": 10}], "1979": [{"min": 58.0, "max": 63.0, "mean": 60.5, "count": 10}], "1980": [{"min": 45.0, "max": 53.0, "mean": 49.3, "count": 10}], "1981": [{"min": 70.0, "max": 74.0, "mean": 72.0, "count": 10}], "1982": [{"min": 10.0, "max": 14.0, "mean": 12.3, "count": 10}], "1983": [{"min": 28.0, "max": 33.0, "mean": 30.8, "count": 10}], "1984": [{"min": 18.0, "max": 22.0, "mean": 20.4, "count": 10}], "1985": [{"min": 57.0, "max": 62.0, "mean": 60.1, "count": 10}], "1986": [{"min": 49.0, "max": 53.0, "mean": 50.7, "count": 10}], "1987": [{"min": 58.0, "max": 63.0, "mean": 60.6, "count": 10}], "1988": [{"min": 16.0, "max": 20.0, "mean": 17.7, "count": 10}], "1989": [{"min": 0.0, "max": 0.0, "mean": 0.0, "count": 10}], "1990": [{"min": 3.0, "max": 8.0, "mean": 6.1, "count": 10}], "1991": [{"min": 14.0, "max": 19.0, "mean": 16.8, "count": 10}], "1992": [{"min": 3.0, "max": 7.0, "mean": 5.1, "count": 10}], "1993": [{"min": 33.0, "max": 38.0, "mean": 35.6, "count": 10}], "1994": [{"min": 6.0, "max": 10.0, "mean": 7.8, "count": 10}], "1995": [{"min": 23.0, "max": 29.0, "mean": 26.4, "count": 10}], "1996": [{"min": 46.0, "max": 50.0, "mean": 47.8, "count": 10}], "1997": [{"min": 26.0, "max": 31.0, "mean": 29.0, "count": 10}], "1998": [{"min": 23.0, "max": 28.0, "mean": 25.5, "count": 10}], "1999": [{"min": 20.0, "max": 24.0, "mean": 22.1, "count": 10}], "2000": [{"min": 5.0, "max": 9.0, "mean": 7.1, "count": 10}], "2001": [{"min": 20.0, "max": 25.0, "mean": 23.1, "count": 10}], "2002": [{"min": 17.0, "max": 22.0, "mean": 19.8, "count": 10}], "2003": [{"min": 21.0, "max": 26.0, "mean": 22.8, "count": 10}], "2004": [{"min": 7.0, "max": 12.0, "mean": 10.1, "count": 10}], "2005": [{"min": 36.0, "max": 40.0, "mean": 37.7, "count": 10}], "2006": [{"min": 22.0, "max": 29.0, "mean": 24.7, "count": 10}], "2007": [{"min": 3.0, "max": 9.0, "mean": 5.5, "count": 10}], "2008": [{"min": 5.0, "max": 10.0, "mean": 7.1, "count": 10}], "2009": [{"min": 27.0, "max": 32.0, "mean": 29.3, "count": 10}], "2010": [{"min": 79.0, "max": 84.0, "mean": 81.1, "count": 10}], "2011": [{"min": 5.0, "max": 10.0, "mean": 7.2, "count": 10}], "2012": [{"min": 23.0, "max": 28.0, "mean": 25.3, "count": 10}], "2013": [{"min": 52.0, "max": 58.0, "mean": 55.1, "count": 10}], "2014": [{"min": 0.0, "max": 5.0, "mean": 2.4, "count": 10}], "2015": [{"min": 1.0, "max": 6.0, "mean": 3.6, "count": 10}], "2016": [{"min": 8.0, "max": 12.0, "mean": 9.5, "count": 10}], "2017": [{"min": 19.0, "max": 25.0, "mean": 22.1, "count": 10}], "2018": [{"min": 6.0, "max": 11.0, "mean": 8.5, "count": 10}], "2019": [{"min": 2.0, "max": 7.0, "mean": 4.3, "count": 10}], "2020": [{"min": 0.0, "max": 0.0, "mean": 0.0, "count": 10}], "2021": [{"min": 28.0, "max": 33.0, "mean": 31.1, "count": 10}], "2022": [{"min": 8.0, "max": 13.0, "mean": 10.3, "count": 10}], "2023": [{"min": 10.0, "max": 15.0, "mean": 12.7, "count": 10}], "2024": [{"min": 0.0, "max": 2.0, "mean": 0.4, "count": 10}], "2025": [{"min": 0.0, "max": 3.0, "mean": 0.9, "count": 10}]}, "summer_days": {"1951": [{"min": 31.0, "max": 32.0, "mean": 31.5, "count": 10}], "1952": [{"min": 38.0, "max": 40.0, "mean": 38.8, "count": 10}], "1953": [{"min": 40.0, "max": 42.0, "mean": 40.7, "count": 10}], "1954": [{"min": 21.0, "max": 22.0, "mean": 21.4, "count": 10}], "1955": [{"min": 23.0, "max": 24.0, "mean": 23.4, "count": 10}], "1956": [{"min": 17.0, "max": 18.0, "mean": 17.4, "count": 10}], "1957": [{"min": 31.0, "max": 32.0, "mean": 31.4, "count": 10}], "1958": [{"min": 27.0, "max": 28.0, "mean": 27.4, "count": 10}], "1959": [{"min": 43.0, "max": 45.0, "mean": 43.6, "count": 10}], "1960": [{"min": 22.0, "max": 24.0, "mean": 22.9, "count": 10}], "1961": [{"min": 35.0, "max": 37.0, "mean": 35.7, "count": 10}], "1962": [{"min": 29.0, "max": 31.0, "mean": 29.7, "count": 10}], "1963": [{"min": 33.0, "max": 35.0, "mean": 33.8, "count": 10}], "1964": [{"min": 47.0, "max": 48.0, "mean": 47.4, "count": 10}], "1965": [{"min": 19.0, "max": 21.0, "mean": 19.9, "count": 10}], "1966": [{"min": 33.0, "max": 34.0, "mean": 33.4, "count": 10}], "1967": [{"min": 33.0, "max": 34.0, "mean": 33.4, "count": 10}], "1968": [{"min": 30.0, "max": 31.0, "mean": 30.5, "count": 10}], "1969": [{"min": 37.0, "max": 39.0, "mean": 37.7, "count": 10}], "1970": [{"min": 31.0, "max": 32.0, "mean": 31.4, "count": 10}], "1971": [{"min": 39.0, "max": 41.0, "mean": 39.8, "count": 10}], "1972": [{"min": 25.0, "max": 27.0, "mean": 26.1, "count": 10}], "1973": [{"min": 41.0, "max": 42.0, "mean": 41.4, "count": 10}], "1974": [{"min": 20.0, "max": 21.0, "mean": 20.4, "count": 10}], "1975": [{"min": 42.0, "max": 43.0, "mean": 42.4, "count": 10}], "1976": [{"min": 44.0, "max": 45.0, "mean": 44.6, "count": 10}], "1977": [{"min": 20.0, "max": 21.0, "mean": 20.4, "count": 10}], "1978": [{"min": 21.0, "max": 23.0, "mean": 21.7, "count": 10}], "1979": [{"min": 28.0, "max": 30.0, "mean": 29.0, "count": 10}], "1980": [{"min": 22.0, "max": 23.0, "mean": 22.4, "count": 10}], "1981": [{"min": 25.0, "max": 27.0, "mean": 25.9, "count": 10}], "1982": [{"min": 50.0, "max": 52.0, "mean": 50.8, "count": 10}], "1983": [{"min": 51.0, "max": 53.0, "mean": 51.6, "count": 10}], "1984": [{"min": 21.0, "max": 22.0, "mean": 21.4, "count": 10}], "1985": [{"min": 29.0, "max": 30.0, "mean": 29.6, "count": 10}], "1986": [{"min": 37.0, "max": 38.0, "mean": 37.5, "count": 10}], "1987": [{"min": 22.0, "max": 23.0, "mean": 22.4, "count": 10}], "1988": [{"min": 32.0, "max": 33.0, "mean": 32.4, "count": 10}], "1989": [{"min": 40.0, "max": 41.0, "mean": 40.4, "count": 10}], "1990": [{"min": 37.0, "max": 38.0, "mean": 37.4, "count": 10}], "1991": [{"min": 41.0, "max": 43.0, "mean": 41.7, "count": 10}], "1992": [{"min": 52.0, "max": 53.0, "mean": 52.4, "count": 10}], "1993": [{"min": 37.0, "max": 39.0, "mean": 37.9, "count": 10}], "1994": [{"min": 44.0, "max": 45.0, "mean": 44.4, "count": 10}], "1995": [{"min": 50.0, "max": 52.0, "mean": 50.7, "count": 10}], "1996": [{"min": 29.0, "max": 30.0, "mean": 29.5, "count": 10}], "1997": [{"min": 45.0, "max": 47.0, "mean": 46.3, "count": 10}], "1998": [{"min": 34.0, "max": 36.0, "mean": 34.6, "count": 10}], "1999": [{"min": 44.0, "max": 45.0, "mean": 44.4, "count": 10}], "2000": [{"min": 37.0, "max": 39.0, "mean": 37.7, "count": 10}], "2001": [{"min": 36.0, "max": 37.0, "mean": 36.4, "count": 10}], "2002": [{"min": 41.0, "max": 43.0, "mean": 41.9, "count": 10}], "2003": [{"min": 65.0, "max": 66.0, "mean": 65.5, "count": 10}], "2004": [{"min": 34.0, "max": 36.0, "mean": 35.0, "count": 10}], "2005": [{"min": 47.0, "max": 48.0, "mean": 47.4, "count": 10}], "2006": [{"min": 61.0, "max": 63.0, "mean": 62.3, "count": 10}], "2007": [{"min": 43.0, "max": 44.0, "mean": 43.4, "count": 10}], "2008": [{"min": 43.0, "max": 45.0, "mean": 43.9, "count": 10}], "2009": [{"min": 43.0, "max": 45.0, "mean": 44.2, "count": 10}], "2010": [{"min": 39.0, "max": 41.0, "mean": 40.3, "count": 10}], "2011": [{"min": 52.0, "max": 55.0, "mean": 53.9, "count": 10}], "2012": [{"min": 44.0, "max": 45.0, "mean": 44.5, "count": 10}], "2013": [{"min": 42.0, "max": 44.0, "mean": 43.2, "count": 10}], "2014": [{"min": 38.0, "max": 39.0, "mean": 38.6, "count": 10}], "2015": [{"min": 50.0, "max": 52.0, "mean": 50.9, "count": 10}], "2016": [{"min": 53.0, "max": 56.0, "mean": 54.9, "count": 10}], "2017": [{"min": 47.0, "max": 49.0, "mean": 48.2, "count": 10}], "2018": [{"min": 84.0, "max": 87.0, "mean": 85.6, "count": 10}], "2019": [{"min": 67.0, "max": 69.0, "mean": 68.1, "count": 10}], "2020": [{"min": 55.0, "max": 58.0, "mean": 56.9, "count": 10}], "2021": [{"min": 44.0, "max": 45.0, "mean": 44.4, "count": 10}], "2022": [{"min": 71.0, "max": 73.0, "mean": 72.2, "count": 10}], "2023": [{"min": 69.0, "max": 70.0, "mean": 69.4, "count": 10}], "2024": [{"min": 66.0, "max": 69.0, "mean": 67.5, "count": 10}], "2025": [{"min": 51.0, "max": 52.0, "mean": 51.4, "count": 10}]}, "sunshine_duration": {"1951": [{"min": 1696.0, "max": 1718.0, "mean": 1703.8, "count": 10}], "1952": [{"min": 1556.0, "max": 1575.0, "mean": 1563.4, "count": 10}], "1953": [{"min": 1741.0, "max": 1751.0, "mean": 1745.2, "count": 10}], "1954": [{"min": 1506.0, "max": 1514.0, "mean": 1510.1, "count": 10}], "1955": [{"min": 1451.0, "max": 1458.0, "mean": 1454.7, "count": 10}], "1956": [{"min": 1380.0, "max": 1389.0, "mean": 1384.6, "count": 10}], "1957": [{"min": 1586.0, "max": 1598.0, "mean": 1590.7, "count": 10}], "1958": [{"min": 1427.0, "max": 1436.0, "mean": 1431.1, "count": 10}], "1959": [{"min": 1924.0, "max": 1936.0, "mean": 1928.6, "count": 10}], "1960": [{"min": 1427.0, "max": 1442.0, "mean": 1432.8, "count": 10}], "1961": [{"min": 1479.0, "max": 1493.0, "mean": 1484.5, "count": 10}], "1962": [{"min": 1545.0, "max": 1561.0, "mean": 1550.4, "count": 10}], "1963": [{"min": 1624.0, "max": 1638.0, "mean": 1628.8, "count": 10}], "1964": [{"min": 1677.0, "max": 1691.0, "mean": 1681.1, "count": 10}], "1965": [{"min": 1451.0, "max": 1465.0, "mean": 1456.4, "count": 10}], "1966": [{"min": 1419.0, "max": 1428.0, "mean": 1423.1, "count": 10}], "1967": [{"min": 1576.0, "max": 1587.0, "mean": 1580.8, "count": 10}], "1968": [{"min": 1509.0, "max": 1523.0, "mean": 1514.3, "count": 10}], "1969": [{"min": 1508.0, "max": 1520.0, "mean": 1512.4, "count": 10}], "1970": [{"min": 1403.0, "max": 1414.0, "mean": 1406.6, "count": 10}], "1971": [{"min": 1664.0, "max": 1682.0, "mean": 1669.6, "count": 10}], "1972": [{"min": 1493.0, "max": 1514.0, "mean": 1500.3, "count": 10}], "1973": [{"min": 1597.0, "max": 1612.0, "mean": 1602.4, "count": 10}], "1974": [{"min": 1356.0, "max": 1375.0, "mean": 1362.7, "count": 10}], "1975": [{"min": 1555.0, "max": 1563.0, "mean": 1557.8, "count": 10}], "1976": [{"min": 1680.0, "max": 1696.0, "mean": 1685.7, "count": 10}], "1977": [{"min": 1274.0, "max": 1284.0, "mean": 1277.6, "count": 10}], "1978": [{"min": 1287.0, "max": 1297.0, "mean": 1290.8, "count": 10}], "1979": [{"min": 1413.0, "max": 1426.0, "mean": 1417.5, "count": 10}], "1980": [{"min": 1419.0, "max": 1432.0, "mean": 1423.7, "count": 10}], "1981": [{"min": 1344.0, "max": 1355.0, "mean": 1347.5, "count": 10}], "1982": [{"min": 1781.0, "max": 1792.0, "mean": 1785.6, "count": 10}], "1983": [{"min": 1587.0, "max": 1600.0, "mean": 1591.4, "count": 10}], "1984": [{"min": 1336.0, "max": 1346.0, "mean": 1340.2, "count": 10}], "1985": [{"min": 1483.0, "max": 1491.0, "mean": 1486.0, "count": 10}], "1986": [{"min": 1467.0, "max": 1473.0, "mean": 1470.4, "count": 10}], "1987": [{"min": 1310.0, "max": 1315.0, "mean": 1312.4, "count": 10}], "1988": [{"min": 1477.0, "max": 1487.0, "mean": 1480.4, "count": 10}], "1989": [{"min": 1772.0, "max": 1781.0, "mean": 1775.8, "count": 10}], "1990": [{"min": 1525.0, "max": 1533.0, "mean": 1529.1, "count": 10}], "1991": [{"min": 1660.0, "max": 1669.0, "mean": 1665.4, "count": 10}], "1992": [{"min": 1615.0, "max": 1629.0, "mean": 1620.5, "count": 10}], "1993": [{"min": 1502.0, "max": 1506.0, "mean": 1504.6, "count": 10}], "1994": [{"min": 1574.0, "max": 1579.0, "mean": 1576.8, "count": 10}], "1995": [{"min": 1562.0, "max": 1572.0, "mean": 1566.4, "count": 10}], "1996": [{"min": 1349.0, "max": 1355.0, "mean": 1351.8, "count": 10}], "1997": [{"min": 1670.0, "max": 1678.0, "mean": 1673.3, "count": 10}], "1998": [{"min": 1461.0, "max": 1476.0, "mean": 1467.7, "count": 10}], "1999": [{"min": 1588.0, "max": 1600.0, "mean": 1593.1, "count": 10}], "2000": [{"min": 1674.0, "max": 1702.0, "mean": 1685.1, "count": 10}], "2001": [{"min": 1480.0, "max": 1489.0, "mean": 1484.3, "count": 10}], "2002": [{"min": 1467.0, "max": 1480.0, "mean": 1471.8, "count": 10}], "2003": [{"min": 1989.0, "max": 1996.0, "mean": 1991.1, "count": 10}], "2004": [{"min": 1618.0, "max": 1629.0, "mean": 1621.8, "count": 10}], "2005": [{"min": 1786.0, "max": 1793.0, "mean": 1788.4, "count": 10}], "2006": [{"min": 1827.0, "max": 1839.0, "mean": 1830.5, "count": 10}], "2007": [{"min": 1690.0, "max": 1697.0, "mean": 1693.6, "count": 10}], "2008": [{"min": 1591.0, "max": 1596.0, "mean": 1592.8, "count": 10}], "2009": [{"min": 1603.0, "max": 1613.0, "mean": 1608.0, "count": 10}], "2010": [{"min": 1526.0, "max": 1537.0, "mean": 1531.0, "count": 10}], "2011": [{"min": 1945.0, "max": 1962.0, "mean": 1952.3, "count": 10}], "2012": [{"min": 1695.0, "max": 1713.0, "mean": 1702.7, "count": 10}], "2013": [{"min": 1459.0, "max": 1478.0, "mean": 1466.7, "count": 10}], "2014": [{"min": 1657.0, "max": 1680.0, "mean": 1667.1, "count": 10}], "2015": [{"min": 1796.0, "max": 1816.0, "mean": 1805.7, "count": 10}], "2016": [{"min": 1635.0, "max": 1652.0, "mean": 1643.3, "count": 10}], "2017": [{"min": 1599.0, "max": 1621.0, "mean": 1608.9, "count": 10}], "2018": [{"min": 1996.0, "max": 2014.0, "mean": 2003.5, "count": 10}], "2019": [{"min": 1873.0, "max": 1892.0, "mean": 1882.3, "count": 10}], "2020": [{"min": 1903.0, "max": 1922.0, "mean": 1910.6, "count": 10}], "2021": [{"min": 1572.0, "max": 1588.0, "mean": 1579.0, "count": 10}], "2022": [{"min": 2045.0, "max": 2061.0, "mean": 2052.1, "count": 10}], "2023": [{"min": 1758.0, "max": 1775.0, "mean": 1764.3, "count": 10}], "2024": [{"min": 1754.0, "max": 1770.0, "mean": 1761.5, "count": 10}], "2025": [{"min": 1892.0, "max": 1895.0, "mean": 1893.6, "count": 10}]}, "vegetation_begin": {"1992": [{"min": 84.0, "max": 86.0, "mean": 84.9, "count": 10}], "1993": [{"min": 89.0, "max": 90.0, "mean": 89.4, "count": 10}], "1994": [{"min": 79.0, "max": 81.0, "mean": 79.6, "count": 10}], "1995": [{"min": 85.0, "max": 87.0, "mean": 85.6, "count": 10}], "1996": [{"min": 109.0, "max": 109.0, "mean": 109.0, "count": 10}], "1997": [{"min": 75.0, "max": 78.0, "mean": 76.5, "count": 10}], "1998": [{"min": 68.0, "max": 70.0, "mean": 68.7, "count": 10}], "1999": [{"min": 80.0, "max": 81.0, "mean": 80.5, "count": 10}], "2000": [{"min": 80.0, "max": 81.0, "mean": 80.5, "count": 10}], "2001": [{"min": 88.0, "max": 89.0, "mean": 88.5, "count": 10}], "2002": [{"min": 64.0, "max": 66.0, "mean": 64.6, "count": 10}], "2003": [{"min": 92.0, "max": 93.0, "mean": 92.5, "count": 10}], "2004": [{"min": 85.0, "max": 86.0, "mean": 85.5, "count": 10}], "2005": [{"min": 90.0, "max": 91.0, "mean": 90.5, "count": 10}], "2006": [{"min": 104.0, "max": 105.0, "mean": 104.1, "count": 10}], "2007": [{"min": 76.0, "max": 77.0, "mean": 76.3, "count": 10}], "2008": [{"min": 64.0, "max": 66.0, "mean": 64.9, "count": 10}], "2009": [{"min": 94.0, "max": 94.0, "mean": 94.0, "count": 10}], "2010": [{"min": 92.0, "max": 93.0, "mean": 92.3, "count": 10}], "2011": [{"min": 85.0, "max": 86.0, "mean": 85.9, "count": 10}], "2012": [{"min": 82.0, "max": 83.0, "mean": 82.3, "count": 10}], "2013": [{"min": 105.0, "max": 106.0, "mean": 105.3, "count": 10}], "2014": [{"min": 71.0, "max": 72.0, "mean": 71.5, "count": 10}], "2015": [{"min": 86.0, "max": 87.0, "mean": 86.5, "count": 10}], "2016": [{"min": 88.0, "max": 89.0, "mean": 88.3, "count": 10}], "2017": [{"min": 83.0, "max": 84.0, "mean": 83.1, "count": 10}], "2018": [{"min": 94.0, "max": 95.0, "mean": 94.5, "count": 10}], "2019": [{"min": 78.0, "max": 79.0, "mean": 78.4, "count": 10}], "2020": [{"min": 67.0, "max": 69.0, "mean": 67.7, "count": 10}], "2021": [{"min": 86.0, "max": 88.0, "mean": 86.8, "count": 10}], "2022": [{"min": 76.0, "max": 78.0, "mean": 77.2, "count": 10}], "2023": [{"min": 74.0, "max": 75.0, "mean": 74.3, "count": 10}], "2024": [{"min": 61.0, "max": 62.0, "mean": 61.4, "count": 10}]}, "vegetation_end": {"1992": [{"min": 307.0, "max": 307.0, "mean": 307.0, "count": 10}], "1993": [{"min": 305.0, "max": 305.0, "mean": 305.0, "count": 10}], "1994": [{"min": 302.0, "max": 303.0, "mean": 302.7, "count": 10}], "1995": [{"min": 311.0, "max": 311.0, "mean": 311.0, "count": 10}], "1996": [{"min": 302.0, "max": 302.0, "mean": 302.0, "count": 10}], "1997": [{"min": 313.0, "max": 313.0, "mean": 313.0, "count": 10}], "1998": [{"min": 304.0, "max": 305.0, "mean": 304.6, "count": 10}], "1999": [{"min": 309.0, "max": 309.0, "mean": 309.0, "count": 10}], "2000": [{"min": 307.0, "max": 307.0, "mean": 307.0, "count": 10}], "2001": [{"min": 313.0, "max": 314.0, "mean": 313.4, "count": 10}], "2002": [{"min": 305.0, "max": 305.0, "mean": 305.0, "count": 10}], "2003": [{"min": 311.0, "max": 311.0, "mean": 311.0, "count": 10}], "2004": [{"min": 307.0, "max": 307.0, "mean": 307.0, "count": 10}], "2005": [{"min": 309.0, "max": 310.0, "mean": 309.1, "count": 10}], "2006": [{"min": 314.0, "max": 314.0, "mean": 314.0, "count": 10}], "2007": [{"min": 306.0, "max": 306.0, "mean": 306.0, "count": 10}], "2008": [{"min": 302.0, "max": 302.0, "mean": 302.0, "count": 10}], "2009": [{"min": 308.0, "max": 309.0, "mean": 308.6, "count": 10}], "2010": [{"min": 306.0, "max": 306.0, "mean": 306.0, "count": 10}], "2011": [{"min": 312.0, "max": 312.0, "mean": 312.0, "count": 10}], "2012": [{"min": 310.0, "max": 311.0, "mean": 310.7, "count": 10}], "2013": [{"min": 306.0, "max": 306.0, "mean": 306.0, "count": 10}], "2014": [{"min": 311.0, "max": 311.0, "mean": 311.0, "count": 10}], "2015": [{"min": 308.0, "max": 308.0, "mean": 308.0, "count": 10}], "2016": [{"min": 314.0, "max": 314.0, "mean": 314.0, "count": 10}], "2017": [{"min": 308.0, "max": 308.0, "mean": 308.0, "count": 10}], "2018": [{"min": 312.0, "max": 312.0, "mean": 312.0, "count": 10}], "2019": [{"min": 315.0, "max": 315.0, "mean": 315.0, "count": 10}], "2020": [{"min": 314.0, "max": 314.0, "mean": 314.0, "count": 10}], "2021": [{"min": 311.0, "max": 312.0, "mean": 311.4, "count": 10}], "2022": [{"min": 314.0, "max": 314.0, "mean": 314.0, "count": 10}], "2023": [{"min": 317.0, "max": 317.0, "mean": 317.0, "count": 10}], "2024": [{"min": 311.0, "max": 312.0, "mean": 311.7, "count": 10}]}}